<?xml version="1.0" encoding="utf-8"?><REarnEstCons><Company><CoName><Name type="Long">Hidili Industry International Devt Ltd.</Name></CoName><CoIds><CoId type="CoId">GL_52701</CoId><CoId type="RepNo">AF9AD</CoId><CoId type="IssueId">1</CoId><CoId type="IssuerID">76216</CoId><CoId type="RedIssueID">55144</CoId><CoId type="IsPrimaryIssue">1</CoId></CoIds><SecurityInfo><Security code="1"><Exchange code="HKG">Hong Kong Stock Exchange</Exchange><Country set="MX" code="HKG">Hong Kong</Country><SecIds><SecId set="LOCAL" type="RIC">1393.HK </SecId><SecId set="LOCAL" type="Display RIC">1393.HK</SecId><SecId set="LOCAL" type="TICKER">1393</SecId><SecId set="LOCAL" type="ISIN">KYG444031069</SecId><SecId set="LOCAL" type="SEDOL">B2471B8</SecId><SecId set="LOCAL" type="CUSIP">G44403106</SecId></SecIds><MarketData><MarketDataItem type="CLPRICE" currCode="CNY" unit="U" updated="2019-08-29T00:00:00">0.241990</MarketDataItem><MarketDataItem type="SHARESOUT" currCode="CNY" unit="U">2045598000</MarketDataItem><MarketDataItem type="MARKETCAP" currCode="CNY" unit="M">495.0135</MarketDataItem><MarketDataItem type="52WKHIGH" currCode="CNY" unit="U" updated="2019-03-27T00:00:00">0.3516</MarketDataItem><MarketDataItem type="52WKLOW" currCode="CNY" unit="U" updated="2019-01-07T00:00:00">0.2182</MarketDataItem></MarketData></Security></SecurityInfo><CompanyInfo><Sector set="RBSS2004" code="50">Energy</Sector><Sector set="RBSS2004" code="501">Energy</Sector><Sector set="RBSS2004" code="5011">Coal</Sector><Sector set="MX" code="ENERGY">Energy</Sector><Industry set="RBSS2004" code="50111">Coal</Industry><Industry set="MX" code="CCOALL">Coal</Industry><Primary type="Earnings">PRX</Primary><Primary type="Consensus">Mean</Primary><Primary type="Estimate">EPS</Primary><Primary type="Periodicity">S</Primary><Currency set="ISO" type="CONSENSUS" code="CNY">Renminbi</Currency><CurFiscalPeriod fYear="2017" fyem="12" periodType="Q" periodNum="1" /><CompanyPeriods><Annual fyNum="-5" fYear="2011" endMonth="12" periodUnit="MNS" periodLength="12"><Interim type="Q" periodNum="1" endMonth="3" endCalYear="2011" periodUnit="MNS" periodLength="3" /><Interim type="Q" periodNum="2" endMonth="6" endCalYear="2011" periodUnit="MNS" periodLength="3" /><Interim type="Q" periodNum="3" endMonth="9" endCalYear="2011" periodUnit="MNS" periodLength="3" /><Interim type="Q" periodNum="4" endMonth="12" endCalYear="2011" periodUnit="MNS" periodLength="3" /><Interim type="S" periodNum="1" endMonth="6" endCalYear="2011" periodUnit="MNS" periodLength="6" /><Interim type="S" periodNum="2" endMonth="12" endCalYear="2011" periodUnit="MNS" periodLength="6" /></Annual><Annual fyNum="-4" fYear="2012" endMonth="12" periodUnit="MNS" periodLength="12"><Interim type="Q" periodNum="1" endMonth="3" endCalYear="2012" periodUnit="MNS" periodLength="3" /><Interim type="Q" periodNum="2" endMonth="6" endCalYear="2012" periodUnit="MNS" periodLength="3" /><Interim type="Q" periodNum="3" endMonth="9" endCalYear="2012" periodUnit="MNS" periodLength="3" /><Interim type="Q" periodNum="4" endMonth="12" endCalYear="2012" periodUnit="MNS" periodLength="3" /><Interim type="S" periodNum="1" endMonth="6" endCalYear="2012" periodUnit="MNS" periodLength="6" /><Interim type="S" periodNum="2" endMonth="12" endCalYear="2012" periodUnit="MNS" periodLength="6" /></Annual><Annual fyNum="-3" fYear="2013" endMonth="12" periodUnit="MNS" periodLength="12"><Interim type="Q" periodNum="1" endMonth="3" endCalYear="2013" periodUnit="MNS" periodLength="3" /><Interim type="Q" periodNum="2" endMonth="6" endCalYear="2013" periodUnit="MNS" periodLength="3" /><Interim type="Q" periodNum="3" endMonth="9" endCalYear="2013" periodUnit="MNS" periodLength="3" /><Interim type="Q" periodNum="4" endMonth="12" endCalYear="2013" periodUnit="MNS" periodLength="3" /><Interim type="S" periodNum="1" endMonth="6" endCalYear="2013" periodUnit="MNS" periodLength="6" /><Interim type="S" periodNum="2" endMonth="12" endCalYear="2013" periodUnit="MNS" periodLength="6" /></Annual><Annual fyNum="-2" fYear="2014" endMonth="12" periodUnit="MNS" periodLength="12"><Interim type="Q" periodNum="1" endMonth="3" endCalYear="2014" periodUnit="MNS" periodLength="3" /><Interim type="Q" periodNum="2" endMonth="6" endCalYear="2014" periodUnit="MNS" periodLength="3" /><Interim type="Q" periodNum="3" endMonth="9" endCalYear="2014" periodUnit="MNS" periodLength="3" /><Interim type="Q" periodNum="4" endMonth="12" endCalYear="2014" periodUnit="MNS" periodLength="3" /><Interim type="S" periodNum="1" endMonth="6" endCalYear="2014" periodUnit="MNS" periodLength="6" /><Interim type="S" periodNum="2" endMonth="12" endCalYear="2014" periodUnit="MNS" periodLength="6" /></Annual><Annual fyNum="-1" fYear="2015" endMonth="12" periodUnit="MNS" periodLength="12"><Interim type="Q" periodNum="1" endMonth="3" endCalYear="2015" periodUnit="MNS" periodLength="3" /><Interim type="Q" periodNum="2" endMonth="6" endCalYear="2015" periodUnit="MNS" periodLength="3" /><Interim type="Q" periodNum="3" endMonth="9" endCalYear="2015" periodUnit="MNS" periodLength="3" /><Interim type="Q" periodNum="4" endMonth="12" endCalYear="2015" periodUnit="MNS" periodLength="3" /><Interim type="S" periodNum="1" endMonth="6" endCalYear="2015" periodUnit="MNS" periodLength="6" /><Interim type="S" periodNum="2" endMonth="12" endCalYear="2015" periodUnit="MNS" periodLength="6" /></Annual><Annual fyNum="0" fYear="2016" endMonth="12" periodUnit="MNS" periodLength="12"><Interim type="Q" periodNum="1" endMonth="3" endCalYear="2016" periodUnit="MNS" periodLength="3" /><Interim type="Q" periodNum="2" endMonth="6" endCalYear="2016" periodUnit="MNS" periodLength="3" /><Interim type="Q" periodNum="3" endMonth="9" endCalYear="2016" periodUnit="MNS" periodLength="3" /><Interim type="Q" periodNum="4" endMonth="12" endCalYear="2016" periodUnit="MNS" periodLength="3" /><Interim type="S" periodNum="1" endMonth="6" endCalYear="2016" periodUnit="MNS" periodLength="6" /><Interim type="S" periodNum="2" endMonth="12" endCalYear="2016" periodUnit="MNS" periodLength="6" /></Annual><Annual fyNum="1" fYear="2017" endMonth="12" periodUnit="MNS" periodLength="12"><Interim type="Q" periodNum="1" endMonth="3" endCalYear="2017" periodUnit="MNS" periodLength="3" /><Interim type="Q" periodNum="2" endMonth="6" endCalYear="2017" periodUnit="MNS" periodLength="3" /><Interim type="Q" periodNum="3" endMonth="9" endCalYear="2017" periodUnit="MNS" periodLength="3" /><Interim type="Q" periodNum="4" endMonth="12" endCalYear="2017" periodUnit="MNS" periodLength="3" /><Interim type="S" periodNum="1" endMonth="6" endCalYear="2017" periodUnit="MNS" periodLength="6" /><Interim type="S" periodNum="2" endMonth="12" endCalYear="2017" periodUnit="MNS" periodLength="6" /></Annual><Annual fyNum="2" fYear="2018" endMonth="12" periodUnit="MNS" periodLength="12"><Interim type="Q" periodNum="1" endMonth="3" endCalYear="2018" periodUnit="MNS" periodLength="3" /><Interim type="Q" periodNum="2" endMonth="6" endCalYear="2018" periodUnit="MNS" periodLength="3" /><Interim type="Q" periodNum="3" endMonth="9" endCalYear="2018" periodUnit="MNS" periodLength="3" /><Interim type="Q" periodNum="4" endMonth="12" endCalYear="2018" periodUnit="MNS" periodLength="3" /><Interim type="S" periodNum="1" endMonth="6" endCalYear="2018" periodUnit="MNS" periodLength="6" /><Interim type="S" periodNum="2" endMonth="12" endCalYear="2018" periodUnit="MNS" periodLength="6" /></Annual><Annual fyNum="3" fYear="2019" endMonth="12" periodUnit="MNS" periodLength="12"><Interim type="Q" periodNum="1" endMonth="3" endCalYear="2019" periodUnit="MNS" periodLength="3" /><Interim type="Q" periodNum="2" endMonth="6" endCalYear="2019" periodUnit="MNS" periodLength="3" /><Interim type="Q" periodNum="3" endMonth="9" endCalYear="2019" periodUnit="MNS" periodLength="3" /><Interim type="Q" periodNum="4" endMonth="12" endCalYear="2019" periodUnit="MNS" periodLength="3" /><Interim type="S" periodNum="1" endMonth="6" endCalYear="2019" periodUnit="MNS" periodLength="6" /><Interim type="S" periodNum="2" endMonth="12" endCalYear="2019" periodUnit="MNS" periodLength="6" /></Annual><Annual fyNum="4" fYear="2020" endMonth="12" periodUnit="MNS" periodLength="12"><Interim type="Q" periodNum="1" endMonth="3" endCalYear="2020" periodUnit="MNS" periodLength="3" /><Interim type="Q" periodNum="2" endMonth="6" endCalYear="2020" periodUnit="MNS" periodLength="3" /><Interim type="Q" periodNum="3" endMonth="9" endCalYear="2020" periodUnit="MNS" periodLength="3" /><Interim type="Q" periodNum="4" endMonth="12" endCalYear="2020" periodUnit="MNS" periodLength="3" /><Interim type="S" periodNum="1" endMonth="6" endCalYear="2020" periodUnit="MNS" periodLength="6" /><Interim type="S" periodNum="2" endMonth="12" endCalYear="2020" periodUnit="MNS" periodLength="6" /></Annual><Annual fyNum="5" fYear="2021" endMonth="12" periodUnit="MNS" periodLength="12"><Interim type="Q" periodNum="1" endMonth="3" endCalYear="2021" periodUnit="MNS" periodLength="3" /><Interim type="Q" periodNum="2" endMonth="6" endCalYear="2021" periodUnit="MNS" periodLength="3" /><Interim type="Q" periodNum="3" endMonth="9" endCalYear="2021" periodUnit="MNS" periodLength="3" /><Interim type="Q" periodNum="4" endMonth="12" endCalYear="2021" periodUnit="MNS" periodLength="3" /><Interim type="S" periodNum="1" endMonth="6" endCalYear="2021" periodUnit="MNS" periodLength="6" /><Interim type="S" periodNum="2" endMonth="12" endCalYear="2021" periodUnit="MNS" periodLength="6" /></Annual></CompanyPeriods></CompanyInfo></Company><Actuals><FYActuals><FYActual type="OPROFIT as of Aug31 2019" unit="M"><FYPeriod endCalYear="2014" endMonth="12" fYear="2014" periodType="A"><ActValue updated="2015-03-31T17:24:21" announceDate="2015-03-31T14:38:00">-786.2900</ActValue></FYPeriod><FYPeriod endCalYear="2013" endMonth="12" fYear="2013" periodType="A"><ActValue updated="2014-04-01T02:47:49" announceDate="2014-04-01T02:38:00">-250.8570</ActValue></FYPeriod><FYPeriod endCalYear="2012" endMonth="12" fYear="2012" periodType="A"><ActValue updated="2013-04-02T06:50:36" announceDate="2013-03-26T23:50:00">424.3780</ActValue></FYPeriod><FYPeriod endCalYear="2011" endMonth="12" fYear="2011" periodType="A"><ActValue updated="2012-04-09T10:22:13" announceDate="2012-03-21T02:24:00">1096.0030</ActValue></FYPeriod></FYActual><FYActual type="NAV as of Aug31 2019" unit="U"><FYPeriod endCalYear="2012" endMonth="12" fYear="2012" periodType="A"><ActValue updated="2013-06-10T08:47:28" announceDate="2013-03-26T23:50:00">3.4600</ActValue></FYPeriod><FYPeriod endCalYear="2011" endMonth="12" fYear="2011" periodType="A"><ActValue updated="2012-04-30T09:48:49" announceDate="2012-03-21T02:24:00">3.6220</ActValue></FYPeriod></FYActual><FYActual type="CAPEX as of Aug31 2019" unit="M"><FYPeriod endCalYear="2013" endMonth="12" fYear="2013" periodType="A"><ActValue updated="2014-04-30T21:38:08" announceDate="2014-04-01T02:38:00">1054.0750</ActValue></FYPeriod><FYPeriod endCalYear="2012" endMonth="12" fYear="2012" periodType="A"><ActValue updated="2013-06-10T08:47:30" announceDate="2013-03-26T23:50:00">1342.0160</ActValue></FYPeriod><FYPeriod endCalYear="2011" endMonth="12" fYear="2011" periodType="A"><ActValue updated="2012-04-30T09:48:50" announceDate="2012-03-21T02:24:00">2184.4180</ActValue></FYPeriod></FYActual><FYActual type="NPROFIT as of Aug31 2019" unit="M"><FYPeriod endCalYear="2014" endMonth="12" fYear="2014" periodType="A"><ActValue updated="2015-03-31T17:24:22" announceDate="2015-03-31T14:38:00">-1422.9510</ActValue></FYPeriod><FYPeriod endCalYear="2013" endMonth="12" fYear="2013" periodType="A"><ActValue updated="2014-04-01T02:47:55" announceDate="2014-04-01T02:38:00">-167.2260</ActValue></FYPeriod><FYPeriod endCalYear="2012" endMonth="12" fYear="2012" periodType="A"><ActValue updated="2013-03-27T00:10:01" announceDate="2013-03-26T23:50:00">-147.3960</ActValue></FYPeriod><FYPeriod endCalYear="2012" endMonth="06" fYear="2012" periodNum="1" periodType="S"><ActValue updated="2012-08-28T00:22:09" announceDate="2012-08-27T23:53:00">186.0550</ActValue></FYPeriod><FYPeriod endCalYear="2011" endMonth="12" fYear="2011" periodType="A"><ActValue updated="2012-03-21T02:29:43" announceDate="2012-03-21T02:28:04">713.6080</ActValue></FYPeriod><FYPeriod endCalYear="2011" endMonth="12" fYear="2011" periodNum="2" periodType="S"><ActValue updated="2012-03-21T02:29:37" announceDate="2012-03-21T02:28:03">453.5220</ActValue></FYPeriod></FYActual><FYActual type="ROA as of Aug31 2019" unit="P"><FYPeriod endCalYear="2014" endMonth="12" fYear="2014" periodType="A"><ActValue updated="2015-05-27T06:05:00" announceDate="2015-03-31T14:38:00">-9.7480</ActValue></FYPeriod><FYPeriod endCalYear="2013" endMonth="12" fYear="2013" periodType="A"><ActValue updated="2014-06-19T12:19:58" announceDate="2014-04-01T02:38:00">-1.0190</ActValue></FYPeriod><FYPeriod endCalYear="2012" endMonth="12" fYear="2012" periodType="A"><ActValue updated="2013-04-02T06:51:45" announceDate="2013-03-26T23:50:00">-0.8790</ActValue></FYPeriod><FYPeriod endCalYear="2011" endMonth="12" fYear="2011" periodType="A"><ActValue updated="2012-04-09T10:22:20" announceDate="2012-03-21T02:24:00">4.6860</ActValue></FYPeriod></FYActual><FYActual type="CPS as of Aug31 2019" unit="U"><FYPeriod endCalYear="2012" endMonth="12" fYear="2012" periodType="A"><ActValue updated="2013-06-10T08:47:25" announceDate="2013-03-26T23:50:00">0.3180</ActValue></FYPeriod><FYPeriod endCalYear="2011" endMonth="12" fYear="2011" periodType="A"><ActValue updated="2012-04-30T09:48:46" announceDate="2012-03-21T02:24:00">0.7620</ActValue></FYPeriod></FYActual><FYActual type="EPS as of Aug31 2019" unit="U"><FYPeriod endCalYear="2014" endMonth="12" fYear="2014" periodType="A"><ActValue updated="2015-03-31T17:24:11" announceDate="2015-03-31T14:38:00">-0.6960</ActValue></FYPeriod><FYPeriod endCalYear="2013" endMonth="12" fYear="2013" periodType="A"><ActValue updated="2014-04-01T02:47:36" announceDate="2014-04-01T02:38:00">-0.0810</ActValue></FYPeriod><FYPeriod endCalYear="2012" endMonth="12" fYear="2012" periodType="A"><ActValue updated="2013-03-27T00:10:03" announceDate="2013-03-26T23:50:00">-0.0710</ActValue></FYPeriod><FYPeriod endCalYear="2011" endMonth="12" fYear="2011" periodType="A"><ActValue updated="2012-03-21T02:29:48" announceDate="2012-03-21T02:24:00">0.3430</ActValue></FYPeriod></FYActual><FYActual type="REVENUE as of Aug31 2019" unit="M"><FYPeriod endCalYear="2014" endMonth="12" fYear="2014" periodType="A"><ActValue updated="2015-03-31T17:24:20" announceDate="2015-03-31T14:38:00">719.8720</ActValue></FYPeriod><FYPeriod endCalYear="2013" endMonth="12" fYear="2013" periodType="A"><ActValue updated="2014-04-01T02:47:46" announceDate="2014-04-01T02:38:00">729.1290</ActValue></FYPeriod><FYPeriod endCalYear="2012" endMonth="12" fYear="2012" periodType="A"><ActValue updated="2013-03-27T00:09:59" announceDate="2013-03-26T23:50:00">1923.5990</ActValue></FYPeriod><FYPeriod endCalYear="2012" endMonth="06" fYear="2012" periodNum="1" periodType="S"><ActValue updated="2012-08-28T00:22:09" announceDate="2012-08-27T23:53:00">1264.2510</ActValue></FYPeriod><FYPeriod endCalYear="2011" endMonth="12" fYear="2011" periodType="A"><ActValue updated="2012-03-21T02:29:42" announceDate="2012-03-21T02:28:04">2861.5320</ActValue></FYPeriod><FYPeriod endCalYear="2011" endMonth="12" fYear="2011" periodNum="2" periodType="S"><ActValue updated="2012-03-21T10:27:23" announceDate="2012-03-21T02:24:00">1734.0000</ActValue></FYPeriod></FYActual><FYActual type="EBIT as of Aug31 2019" unit="M"><FYPeriod endCalYear="2014" endMonth="12" fYear="2014" periodType="A"><ActValue updated="2015-03-31T17:24:21" announceDate="2015-03-31T14:38:00">-786.2900</ActValue></FYPeriod><FYPeriod endCalYear="2013" endMonth="12" fYear="2013" periodType="A"><ActValue updated="2014-04-01T02:47:50" announceDate="2014-04-01T02:38:00">-250.8570</ActValue></FYPeriod><FYPeriod endCalYear="2012" endMonth="12" fYear="2012" periodType="A"><ActValue updated="2013-04-02T06:51:40" announceDate="2013-03-26T23:50:00">424.3780</ActValue></FYPeriod><FYPeriod endCalYear="2011" endMonth="12" fYear="2011" periodType="A"><ActValue updated="2012-04-09T10:22:15" announceDate="2012-03-21T02:24:00">1230.3940</ActValue></FYPeriod></FYActual><FYActual type="BVPS as of Aug31 2019" unit="U"><FYPeriod endCalYear="2014" endMonth="12" fYear="2014" periodType="A"><ActValue updated="2015-04-03T13:50:51" announceDate="2015-03-31T14:38:00">2.7203</ActValue></FYPeriod><FYPeriod endCalYear="2013" endMonth="12" fYear="2013" periodType="A"><ActValue updated="2014-04-03T08:08:19" announceDate="2014-04-01T02:38:00">3.3820</ActValue></FYPeriod><FYPeriod endCalYear="2012" endMonth="12" fYear="2012" periodType="A"><ActValue updated="2013-06-10T08:47:27" announceDate="2013-03-26T23:50:00">3.5270</ActValue></FYPeriod><FYPeriod endCalYear="2011" endMonth="12" fYear="2011" periodType="A"><ActValue updated="2012-04-30T09:48:48" announceDate="2012-03-21T02:24:00">3.6910</ActValue></FYPeriod></FYActual><FYActual type="NPROFITREP as of Aug31 2019" unit="M"><FYPeriod endCalYear="2014" endMonth="12" fYear="2014" periodType="A"><ActValue updated="2015-03-31T17:24:22" announceDate="2015-03-31T14:38:00">-1422.9510</ActValue></FYPeriod><FYPeriod endCalYear="2013" endMonth="12" fYear="2013" periodType="A"><ActValue updated="2014-04-01T02:47:56" announceDate="2014-04-01T02:38:00">-424.6970</ActValue></FYPeriod><FYPeriod endCalYear="2012" endMonth="12" fYear="2012" periodType="A"><ActValue updated="2013-03-27T00:10:02" announceDate="2013-03-26T23:50:00">-147.3960</ActValue></FYPeriod><FYPeriod endCalYear="2012" endMonth="06" fYear="2012" periodNum="1" periodType="S"><ActValue updated="2012-08-28T00:22:10" announceDate="2012-08-27T23:53:00">186.0550</ActValue></FYPeriod><FYPeriod endCalYear="2011" endMonth="12" fYear="2011" periodType="A"><ActValue updated="2012-03-21T02:29:46" announceDate="2012-03-21T02:28:04">713.6080</ActValue></FYPeriod><FYPeriod endCalYear="2011" endMonth="12" fYear="2011" periodNum="2" periodType="S"><ActValue updated="2012-03-21T02:29:39" announceDate="2012-03-21T02:28:03">453.5220</ActValue></FYPeriod></FYActual><FYActual type="PPROFIT as of Aug31 2019" unit="M"><FYPeriod endCalYear="2014" endMonth="12" fYear="2014" periodType="A"><ActValue updated="2015-03-31T17:24:21" announceDate="2015-03-31T14:38:00">-1354.3960</ActValue></FYPeriod><FYPeriod endCalYear="2013" endMonth="12" fYear="2013" periodType="A"><ActValue updated="2014-04-01T02:47:51" announceDate="2014-04-01T02:38:00">-166.3160</ActValue></FYPeriod><FYPeriod endCalYear="2012" endMonth="12" fYear="2012" periodType="A"><ActValue updated="2013-04-02T06:51:41" announceDate="2013-03-26T23:50:00">-54.8570</ActValue></FYPeriod><FYPeriod endCalYear="2012" endMonth="06" fYear="2012" periodNum="1" periodType="S"><ActValue updated="2012-08-30T04:37:04" announceDate="2012-08-27T23:53:00">279.6880</ActValue></FYPeriod><FYPeriod endCalYear="2011" endMonth="12" fYear="2011" periodType="A"><ActValue updated="2012-03-21T02:29:45" announceDate="2012-03-21T02:28:04">931.2760</ActValue></FYPeriod><FYPeriod endCalYear="2011" endMonth="12" fYear="2011" periodNum="2" periodType="S"><ActValue updated="2012-03-21T02:29:32" announceDate="2012-03-21T02:28:03">593.7510</ActValue></FYPeriod></FYActual><FYActual type="EPSREP as of Aug31 2019" unit="U"><FYPeriod endCalYear="2014" endMonth="12" fYear="2014" periodType="A"><ActValue updated="2015-03-31T17:24:20" announceDate="2015-03-31T14:38:00">-0.6960</ActValue></FYPeriod><FYPeriod endCalYear="2013" endMonth="12" fYear="2013" periodType="A"><ActValue updated="2014-04-01T02:47:37" announceDate="2014-04-01T02:38:00">-0.2060</ActValue></FYPeriod><FYPeriod endCalYear="2012" endMonth="12" fYear="2012" periodType="A"><ActValue updated="2013-03-27T00:10:04" announceDate="2013-03-26T23:50:00">-0.0710</ActValue></FYPeriod><FYPeriod endCalYear="2011" endMonth="12" fYear="2011" periodType="A"><ActValue updated="2012-03-21T02:29:50" announceDate="2012-03-21T02:24:00">0.3430</ActValue></FYPeriod></FYActual><FYActual type="PPROFITREP as of Aug31 2019" unit="M"><FYPeriod endCalYear="2013" endMonth="12" fYear="2013" periodType="A"><ActValue updated="2014-04-01T02:47:53" announceDate="2014-04-01T02:38:00">-166.3160</ActValue></FYPeriod><FYPeriod endCalYear="2012" endMonth="12" fYear="2012" periodType="A"><ActValue updated="2013-03-27T00:10:00" announceDate="2013-03-26T23:50:00">-54.8570</ActValue></FYPeriod><FYPeriod endCalYear="2012" endMonth="06" fYear="2012" periodNum="1" periodType="S"><ActValue updated="2012-08-30T04:37:05" announceDate="2012-08-27T23:53:00">279.6880</ActValue></FYPeriod><FYPeriod endCalYear="2011" endMonth="12" fYear="2011" periodType="A"><ActValue updated="2012-03-21T02:29:47" announceDate="2012-03-21T02:28:04">931.2760</ActValue></FYPeriod><FYPeriod endCalYear="2011" endMonth="12" fYear="2011" periodNum="2" periodType="S"><ActValue updated="2012-03-21T02:29:34" announceDate="2012-03-21T02:28:03">593.7510</ActValue></FYPeriod></FYActual><FYActual type="EBITDA as of Aug31 2019" unit="M"><FYPeriod endCalYear="2014" endMonth="12" fYear="2014" periodType="A"><ActValue updated="2015-03-31T17:24:21" announceDate="2015-03-31T14:38:00">-176.4230</ActValue></FYPeriod><FYPeriod endCalYear="2013" endMonth="12" fYear="2013" periodType="A"><ActValue updated="2014-04-01T02:47:48" announceDate="2014-04-01T02:38:00">-165.0330</ActValue></FYPeriod><FYPeriod endCalYear="2012" endMonth="12" fYear="2012" periodType="A"><ActValue updated="2013-04-02T06:50:34" announceDate="2013-03-26T23:50:00">579.1020</ActValue></FYPeriod><FYPeriod endCalYear="2011" endMonth="12" fYear="2011" periodType="A"><ActValue updated="2012-04-09T10:22:12" announceDate="2012-03-21T02:24:00">1399.4490</ActValue></FYPeriod></FYActual><FYActual type="NDEBT as of Aug31 2019" unit="M"><FYPeriod endCalYear="2014" endMonth="12" fYear="2014" periodType="A"><ActValue updated="2015-05-27T06:05:00" announceDate="2015-03-31T14:38:00">7121.5310</ActValue></FYPeriod><FYPeriod endCalYear="2013" endMonth="12" fYear="2013" periodType="A"><ActValue updated="2014-06-19T12:19:55" announceDate="2014-04-01T02:38:00">5008.3520</ActValue></FYPeriod><FYPeriod endCalYear="2012" endMonth="12" fYear="2012" periodType="A"><ActValue updated="2013-04-02T06:51:42" announceDate="2013-03-26T23:50:00">7167.6680</ActValue></FYPeriod><FYPeriod endCalYear="2011" endMonth="12" fYear="2011" periodType="A"><ActValue updated="2012-04-09T10:22:17" announceDate="2012-03-21T02:24:00">5492.3300</ActValue></FYPeriod></FYActual><FYActual type="ROE as of Aug31 2019" unit="P"><FYPeriod endCalYear="2014" endMonth="12" fYear="2014" periodType="A"><ActValue updated="2015-05-27T06:05:04" announceDate="2015-03-31T14:38:00">-22.6840</ActValue></FYPeriod><FYPeriod endCalYear="2013" endMonth="12" fYear="2013" periodType="A"><ActValue updated="2014-06-19T12:19:59" announceDate="2014-04-01T02:38:00">-2.3440</ActValue></FYPeriod><FYPeriod endCalYear="2012" endMonth="12" fYear="2012" periodType="A"><ActValue updated="2013-04-02T06:51:44" announceDate="2013-03-26T23:50:00">-1.9860</ActValue></FYPeriod><FYPeriod endCalYear="2011" endMonth="12" fYear="2011" periodType="A"><ActValue updated="2012-04-09T10:22:18" announceDate="2012-03-21T02:24:00">9.7780</ActValue></FYPeriod></FYActual><FYActual type="DPS as of Aug31 2019" unit="U"><FYPeriod endCalYear="2014" endMonth="12" fYear="2014" periodType="A"><ActValue updated="2015-03-31T17:24:22" announceDate="2015-03-31T14:38:00">0.0000</ActValue></FYPeriod><FYPeriod endCalYear="2012" endMonth="12" fYear="2012" periodType="A"><ActValue updated="2013-03-27T00:10:05" announceDate="2013-03-26T23:50:00">0.0000</ActValue></FYPeriod><FYPeriod endCalYear="2011" endMonth="12" fYear="2011" periodType="A"><ActValue updated="2012-04-09T10:22:16" announceDate="2012-03-21T02:24:00">0.0690</ActValue></FYPeriod></FYActual></FYActuals></Actuals><ConsEstimates><FYEstimates><FYEstimate type="BVPS as of Aug31 2019" unit="U"><FYPeriod endCalYear="2011" endMonth="12" fYear="2011" periodType="A"><ConsEstimate type="High"><ConsValue dateType="CURR">5.5400</ConsValue></ConsEstimate><ConsEstimate type="Low"><ConsValue dateType="CURR">3.6160</ConsValue></ConsEstimate><ConsEstimate type="Mean"><ConsValue dateType="CURR">4.0133</ConsValue></ConsEstimate><ConsEstimate type="Median"><ConsValue dateType="CURR">3.6600</ConsValue></ConsEstimate><ConsEstimate type="StdDev"><ConsValue dateType="CURR">0.6292</ConsValue></ConsEstimate><ConsEstimate type="NumOfEst"><ConsValue dateType="CURR">8</ConsValue></ConsEstimate></FYPeriod><FYPeriod endCalYear="2012" endMonth="12" fYear="2012" periodType="A"><ConsEstimate type="High"><ConsValue dateType="CURR">4.4440</ConsValue></ConsEstimate><ConsEstimate type="Low"><ConsValue dateType="CURR">1.4000</ConsValue></ConsEstimate><ConsEstimate type="Mean"><ConsValue dateType="CURR">3.4850</ConsValue></ConsEstimate><ConsEstimate type="Median"><ConsValue dateType="CURR">3.6620</ConsValue></ConsEstimate><ConsEstimate type="StdDev"><ConsValue dateType="CURR">0.7469</ConsValue></ConsEstimate><ConsEstimate type="NumOfEst"><ConsValue dateType="CURR">10</ConsValue></ConsEstimate></FYPeriod><FYPeriod endCalYear="2013" endMonth="12" fYear="2013" periodType="A"><ConsEstimate type="High"><ConsValue dateType="CURR">3.5020</ConsValue></ConsEstimate><ConsEstimate type="Low"><ConsValue dateType="CURR">3.2340</ConsValue></ConsEstimate><ConsEstimate type="Mean"><ConsValue dateType="CURR">3.4292</ConsValue></ConsEstimate><ConsEstimate type="Median"><ConsValue dateType="CURR">3.4900</ConsValue></ConsEstimate><ConsEstimate type="StdDev"><ConsValue dateType="CURR">0.1020</ConsValue></ConsEstimate><ConsEstimate type="NumOfEst"><ConsValue dateType="CURR">5</ConsValue></ConsEstimate></FYPeriod><FYPeriod endCalYear="2013" endMonth="09" fYear="2013" periodNum="3" periodType="Q"><ConsEstimate type="High"><ConsValue dateType="CURR">3.3600</ConsValue></ConsEstimate><ConsEstimate type="Low"><ConsValue dateType="CURR">3.3600</ConsValue></ConsEstimate><ConsEstimate type="Mean"><ConsValue dateType="CURR">3.3600</ConsValue></ConsEstimate><ConsEstimate type="Median"><ConsValue dateType="CURR">3.3600</ConsValue></ConsEstimate><ConsEstimate type="StdDev"><ConsValue dateType="CURR">0.0000</ConsValue></ConsEstimate><ConsEstimate type="NumOfEst"><ConsValue dateType="CURR">1</ConsValue></ConsEstimate></FYPeriod><FYPeriod endCalYear="2014" endMonth="12" fYear="2014" periodType="A"><ConsEstimate type="High"><ConsValue dateType="CURR">3.0830</ConsValue></ConsEstimate><ConsEstimate type="Low"><ConsValue dateType="CURR">2.8740</ConsValue></ConsEstimate><ConsEstimate type="Mean"><ConsValue dateType="CURR">2.9785</ConsValue></ConsEstimate><ConsEstimate type="Median"><ConsValue dateType="CURR">2.9785</ConsValue></ConsEstimate><ConsEstimate type="StdDev"><ConsValue dateType="CURR">0.1045</ConsValue></ConsEstimate><ConsEstimate type="NumOfEst"><ConsValue dateType="CURR">2</ConsValue></ConsEstimate></FYPeriod></FYEstimate><FYEstimate type="CAPEX as of Aug31 2019" unit="M"><FYPeriod endCalYear="2011" endMonth="12" fYear="2011" periodType="A"><ConsEstimate type="High"><ConsValue dateType="CURR">1570.0000</ConsValue></ConsEstimate><ConsEstimate type="Low"><ConsValue dateType="CURR">1064.0000</ConsValue></ConsEstimate><ConsEstimate type="Mean"><ConsValue dateType="CURR">1283.5556</ConsValue></ConsEstimate><ConsEstimate type="Median"><ConsValue dateType="CURR">1300.0000</ConsValue></ConsEstimate><ConsEstimate type="StdDev"><ConsValue dateType="CURR">153.7119</ConsValue></ConsEstimate><ConsEstimate type="NumOfEst"><ConsValue dateType="CURR">9</ConsValue></ConsEstimate></FYPeriod><FYPeriod endCalYear="2011" endMonth="09" fYear="2011" periodNum="3" periodType="Q"><ConsEstimate type="High"><ConsValue dateType="CURR">368.0000</ConsValue></ConsEstimate><ConsEstimate type="Low"><ConsValue dateType="CURR">368.0000</ConsValue></ConsEstimate><ConsEstimate type="Mean"><ConsValue dateType="CURR">368.0000</ConsValue></ConsEstimate><ConsEstimate type="Median"><ConsValue dateType="CURR">368.0000</ConsValue></ConsEstimate><ConsEstimate type="StdDev"><ConsValue dateType="CURR">0.0000</ConsValue></ConsEstimate><ConsEstimate type="NumOfEst"><ConsValue dateType="CURR">1</ConsValue></ConsEstimate></FYPeriod><FYPeriod endCalYear="2012" endMonth="12" fYear="2012" periodType="A"><ConsEstimate type="High"><ConsValue dateType="CURR">1350.7940</ConsValue></ConsEstimate><ConsEstimate type="Low"><ConsValue dateType="CURR">850.0000</ConsValue></ConsEstimate><ConsEstimate type="Mean"><ConsValue dateType="CURR">1063.0316</ConsValue></ConsEstimate><ConsEstimate type="Median"><ConsValue dateType="CURR">1030.6040</ConsValue></ConsEstimate><ConsEstimate type="StdDev"><ConsValue dateType="CURR">184.5056</ConsValue></ConsEstimate><ConsEstimate type="NumOfEst"><ConsValue dateType="CURR">8</ConsValue></ConsEstimate></FYPeriod><FYPeriod endCalYear="2013" endMonth="12" fYear="2013" periodType="A"><ConsEstimate type="High"><ConsValue dateType="CURR">1383.9550</ConsValue></ConsEstimate><ConsEstimate type="Low"><ConsValue dateType="CURR">532.4110</ConsValue></ConsEstimate><ConsEstimate type="Mean"><ConsValue dateType="CURR">899.0915</ConsValue></ConsEstimate><ConsEstimate type="Median"><ConsValue dateType="CURR">840.0000</ConsValue></ConsEstimate><ConsEstimate type="StdDev"><ConsValue dateType="CURR">314.8535</ConsValue></ConsEstimate><ConsEstimate type="NumOfEst"><ConsValue dateType="CURR">4</ConsValue></ConsEstimate></FYPeriod><FYPeriod endCalYear="2014" endMonth="12" fYear="2014" periodType="A"><ConsEstimate type="High"><ConsValue dateType="CURR">385.4500</ConsValue></ConsEstimate><ConsEstimate type="Low"><ConsValue dateType="CURR">385.4500</ConsValue></ConsEstimate><ConsEstimate type="Mean"><ConsValue dateType="CURR">385.4500</ConsValue></ConsEstimate><ConsEstimate type="Median"><ConsValue dateType="CURR">385.4500</ConsValue></ConsEstimate><ConsEstimate type="StdDev"><ConsValue dateType="CURR">0.0000</ConsValue></ConsEstimate><ConsEstimate type="NumOfEst"><ConsValue dateType="CURR">1</ConsValue></ConsEstimate></FYPeriod></FYEstimate><FYEstimate type="CPS as of Aug31 2019" unit="U"><FYPeriod endCalYear="2011" endMonth="12" fYear="2011" periodType="A"><ConsEstimate type="High"><ConsValue dateType="CURR">0.6630</ConsValue></ConsEstimate><ConsEstimate type="Low"><ConsValue dateType="CURR">0.3900</ConsValue></ConsEstimate><ConsEstimate type="Mean"><ConsValue dateType="CURR">0.4868</ConsValue></ConsEstimate><ConsEstimate type="Median"><ConsValue dateType="CURR">0.4790</ConsValue></ConsEstimate><ConsEstimate type="StdDev"><ConsValue dateType="CURR">0.0884</ConsValue></ConsEstimate><ConsEstimate type="NumOfEst"><ConsValue dateType="CURR">6</ConsValue></ConsEstimate></FYPeriod><FYPeriod endCalYear="2012" endMonth="12" fYear="2012" periodType="A"><ConsEstimate type="High"><ConsValue dateType="CURR">0.4070</ConsValue></ConsEstimate><ConsEstimate type="Low"><ConsValue dateType="CURR">0.0900</ConsValue></ConsEstimate><ConsEstimate type="Mean"><ConsValue dateType="CURR">0.2286</ConsValue></ConsEstimate><ConsEstimate type="Median"><ConsValue dateType="CURR">0.2160</ConsValue></ConsEstimate><ConsEstimate type="StdDev"><ConsValue dateType="CURR">0.1020</ConsValue></ConsEstimate><ConsEstimate type="NumOfEst"><ConsValue dateType="CURR">5</ConsValue></ConsEstimate></FYPeriod><FYPeriod endCalYear="2013" endMonth="12" fYear="2013" periodType="A"><ConsEstimate type="High"><ConsValue dateType="CURR">0.2600</ConsValue></ConsEstimate><ConsEstimate type="Low"><ConsValue dateType="CURR">0.1300</ConsValue></ConsEstimate><ConsEstimate type="Mean"><ConsValue dateType="CURR">0.1950</ConsValue></ConsEstimate><ConsEstimate type="Median"><ConsValue dateType="CURR">0.1950</ConsValue></ConsEstimate><ConsEstimate type="StdDev"><ConsValue dateType="CURR">0.0650</ConsValue></ConsEstimate><ConsEstimate type="NumOfEst"><ConsValue dateType="CURR">2</ConsValue></ConsEstimate></FYPeriod><FYPeriod endCalYear="2013" endMonth="09" fYear="2013" periodNum="3" periodType="Q"><ConsEstimate type="High"><ConsValue dateType="CURR">0.3500</ConsValue></ConsEstimate><ConsEstimate type="Low"><ConsValue dateType="CURR">0.3500</ConsValue></ConsEstimate><ConsEstimate type="Mean"><ConsValue dateType="CURR">0.3500</ConsValue></ConsEstimate><ConsEstimate type="Median"><ConsValue dateType="CURR">0.3500</ConsValue></ConsEstimate><ConsEstimate type="StdDev"><ConsValue dateType="CURR">0.0000</ConsValue></ConsEstimate><ConsEstimate type="NumOfEst"><ConsValue dateType="CURR">1</ConsValue></ConsEstimate></FYPeriod><FYPeriod endCalYear="2014" endMonth="12" fYear="2014" periodType="A"><ConsEstimate type="High"><ConsValue dateType="CURR">-0.5020</ConsValue></ConsEstimate><ConsEstimate type="Low"><ConsValue dateType="CURR">-0.5020</ConsValue></ConsEstimate><ConsEstimate type="Mean"><ConsValue dateType="CURR">-0.5020</ConsValue></ConsEstimate><ConsEstimate type="Median"><ConsValue dateType="CURR">-0.5020</ConsValue></ConsEstimate><ConsEstimate type="StdDev"><ConsValue dateType="CURR">0.0000</ConsValue></ConsEstimate><ConsEstimate type="NumOfEst"><ConsValue dateType="CURR">1</ConsValue></ConsEstimate></FYPeriod></FYEstimate><FYEstimate type="DPS as of Aug31 2019" unit="U"><FYPeriod endCalYear="2011" endMonth="12" fYear="2011" periodType="A"><ConsEstimate type="High"><ConsValue dateType="CURR">0.1000</ConsValue></ConsEstimate><ConsEstimate type="Low"><ConsValue dateType="CURR">0.0000</ConsValue></ConsEstimate><ConsEstimate type="Mean"><ConsValue dateType="CURR">0.0546</ConsValue></ConsEstimate><ConsEstimate type="Median"><ConsValue dateType="CURR">0.0653</ConsValue></ConsEstimate><ConsEstimate type="StdDev"><ConsValue dateType="CURR">0.0316</ConsValue></ConsEstimate><ConsEstimate type="NumOfEst"><ConsValue dateType="CURR">14</ConsValue></ConsEstimate></FYPeriod><FYPeriod endCalYear="2012" endMonth="12" fYear="2012" periodType="A"><ConsEstimate type="High"><ConsValue dateType="CURR">0.0690</ConsValue></ConsEstimate><ConsEstimate type="Low"><ConsValue dateType="CURR">0.0000</ConsValue></ConsEstimate><ConsEstimate type="Mean"><ConsValue dateType="CURR">0.0213</ConsValue></ConsEstimate><ConsEstimate type="Median"><ConsValue dateType="CURR">0.0180</ConsValue></ConsEstimate><ConsEstimate type="StdDev"><ConsValue dateType="CURR">0.0211</ConsValue></ConsEstimate><ConsEstimate type="NumOfEst"><ConsValue dateType="CURR">14</ConsValue></ConsEstimate></FYPeriod><FYPeriod endCalYear="2013" endMonth="12" fYear="2013" periodType="A"><ConsEstimate type="High"><ConsValue dateType="CURR">0.0200</ConsValue></ConsEstimate><ConsEstimate type="Low"><ConsValue dateType="CURR">0.0000</ConsValue></ConsEstimate><ConsEstimate type="Mean"><ConsValue dateType="CURR">0.0033</ConsValue></ConsEstimate><ConsEstimate type="Median"><ConsValue dateType="CURR">0.0000</ConsValue></ConsEstimate><ConsEstimate type="StdDev"><ConsValue dateType="CURR">0.0075</ConsValue></ConsEstimate><ConsEstimate type="NumOfEst"><ConsValue dateType="CURR">6</ConsValue></ConsEstimate></FYPeriod><FYPeriod endCalYear="2013" endMonth="09" fYear="2013" periodNum="3" periodType="Q"><ConsEstimate type="High"><ConsValue dateType="CURR">0.0000</ConsValue></ConsEstimate><ConsEstimate type="Low"><ConsValue dateType="CURR">0.0000</ConsValue></ConsEstimate><ConsEstimate type="Mean"><ConsValue dateType="CURR">0.0000</ConsValue></ConsEstimate><ConsEstimate type="Median"><ConsValue dateType="CURR">0.0000</ConsValue></ConsEstimate><ConsEstimate type="StdDev"><ConsValue dateType="CURR">0.0000</ConsValue></ConsEstimate><ConsEstimate type="NumOfEst"><ConsValue dateType="CURR">1</ConsValue></ConsEstimate></FYPeriod><FYPeriod endCalYear="2014" endMonth="12" fYear="2014" periodType="A"><ConsEstimate type="High"><ConsValue dateType="CURR">0.0000</ConsValue></ConsEstimate><ConsEstimate type="Low"><ConsValue dateType="CURR">0.0000</ConsValue></ConsEstimate><ConsEstimate type="Mean"><ConsValue dateType="CURR">0.0000</ConsValue></ConsEstimate><ConsEstimate type="Median"><ConsValue dateType="CURR">0.0000</ConsValue></ConsEstimate><ConsEstimate type="StdDev"><ConsValue dateType="CURR">0.0000</ConsValue></ConsEstimate><ConsEstimate type="NumOfEst"><ConsValue dateType="CURR">2</ConsValue></ConsEstimate></FYPeriod></FYEstimate><FYEstimate type="EBIT as of Aug31 2019" unit="M"><FYPeriod endCalYear="2011" endMonth="12" fYear="2011" periodType="A"><ConsEstimate type="High"><ConsValue dateType="CURR">1990.2115</ConsValue></ConsEstimate><ConsEstimate type="Low"><ConsValue dateType="CURR">1121.0000</ConsValue></ConsEstimate><ConsEstimate type="Mean"><ConsValue dateType="CURR">1248.0240</ConsValue></ConsEstimate><ConsEstimate type="Median"><ConsValue dateType="CURR">1187.3160</ConsValue></ConsEstimate><ConsEstimate type="StdDev"><ConsValue dateType="CURR">217.4728</ConsValue></ConsEstimate><ConsEstimate type="NumOfEst"><ConsValue dateType="CURR">13</ConsValue></ConsEstimate></FYPeriod><FYPeriod endCalYear="2012" endMonth="12" fYear="2012" periodType="A"><ConsEstimate type="High"><ConsValue dateType="CURR">882.0000</ConsValue></ConsEstimate><ConsEstimate type="Low"><ConsValue dateType="CURR">263.0000</ConsValue></ConsEstimate><ConsEstimate type="Mean"><ConsValue dateType="CURR">624.5265</ConsValue></ConsEstimate><ConsEstimate type="Median"><ConsValue dateType="CURR">626.8340</ConsValue></ConsEstimate><ConsEstimate type="StdDev"><ConsValue dateType="CURR">152.4387</ConsValue></ConsEstimate><ConsEstimate type="NumOfEst"><ConsValue dateType="CURR">14</ConsValue></ConsEstimate></FYPeriod><FYPeriod endCalYear="2013" endMonth="12" fYear="2013" periodType="A"><ConsEstimate type="High"><ConsValue dateType="CURR">444.3920</ConsValue></ConsEstimate><ConsEstimate type="Low"><ConsValue dateType="CURR">-206.7090</ConsValue></ConsEstimate><ConsEstimate type="Mean"><ConsValue dateType="CURR">70.0068</ConsValue></ConsEstimate><ConsEstimate type="Median"><ConsValue dateType="CURR">31.1790</ConsValue></ConsEstimate><ConsEstimate type="StdDev"><ConsValue dateType="CURR">259.4214</ConsValue></ConsEstimate><ConsEstimate type="NumOfEst"><ConsValue dateType="CURR">6</ConsValue></ConsEstimate></FYPeriod><FYPeriod endCalYear="2014" endMonth="12" fYear="2014" periodType="A"><ConsEstimate type="High"><ConsValue dateType="CURR">-140.5210</ConsValue></ConsEstimate><ConsEstimate type="Low"><ConsValue dateType="CURR">-189.2700</ConsValue></ConsEstimate><ConsEstimate type="Mean"><ConsValue dateType="CURR">-164.8955</ConsValue></ConsEstimate><ConsEstimate type="Median"><ConsValue dateType="CURR">-164.8955</ConsValue></ConsEstimate><ConsEstimate type="StdDev"><ConsValue dateType="CURR">24.3745</ConsValue></ConsEstimate><ConsEstimate type="NumOfEst"><ConsValue dateType="CURR">2</ConsValue></ConsEstimate></FYPeriod></FYEstimate><FYEstimate type="EBITDA as of Aug31 2019" unit="M"><FYPeriod endCalYear="2011" endMonth="12" fYear="2011" periodType="A"><ConsEstimate type="High"><ConsValue dateType="CURR">1496.0000</ConsValue></ConsEstimate><ConsEstimate type="Low"><ConsValue dateType="CURR">1180.1180</ConsValue></ConsEstimate><ConsEstimate type="Mean"><ConsValue dateType="CURR">1326.0021</ConsValue></ConsEstimate><ConsEstimate type="Median"><ConsValue dateType="CURR">1310.4000</ConsValue></ConsEstimate><ConsEstimate type="StdDev"><ConsValue dateType="CURR">76.5364</ConsValue></ConsEstimate><ConsEstimate type="NumOfEst"><ConsValue dateType="CURR">14</ConsValue></ConsEstimate></FYPeriod><FYPeriod endCalYear="2012" endMonth="12" fYear="2012" periodType="A"><ConsEstimate type="High"><ConsValue dateType="CURR">1056.0000</ConsValue></ConsEstimate><ConsEstimate type="Low"><ConsValue dateType="CURR">417.0000</ConsValue></ConsEstimate><ConsEstimate type="Mean"><ConsValue dateType="CURR">805.8058</ConsValue></ConsEstimate><ConsEstimate type="Median"><ConsValue dateType="CURR">840.3730</ConsValue></ConsEstimate><ConsEstimate type="StdDev"><ConsValue dateType="CURR">163.9986</ConsValue></ConsEstimate><ConsEstimate type="NumOfEst"><ConsValue dateType="CURR">13</ConsValue></ConsEstimate></FYPeriod><FYPeriod endCalYear="2013" endMonth="12" fYear="2013" periodType="A"><ConsEstimate type="High"><ConsValue dateType="CURR">394.2930</ConsValue></ConsEstimate><ConsEstimate type="Low"><ConsValue dateType="CURR">65.3650</ConsValue></ConsEstimate><ConsEstimate type="Mean"><ConsValue dateType="CURR">178.5527</ConsValue></ConsEstimate><ConsEstimate type="Median"><ConsValue dateType="CURR">76.0000</ConsValue></ConsEstimate><ConsEstimate type="StdDev"><ConsValue dateType="CURR">152.6132</ConsValue></ConsEstimate><ConsEstimate type="NumOfEst"><ConsValue dateType="CURR">3</ConsValue></ConsEstimate></FYPeriod><FYPeriod endCalYear="2014" endMonth="12" fYear="2014" periodType="A"><ConsEstimate type="High"><ConsValue dateType="CURR">-45.1440</ConsValue></ConsEstimate><ConsEstimate type="Low"><ConsValue dateType="CURR">-64.1570</ConsValue></ConsEstimate><ConsEstimate type="Mean"><ConsValue dateType="CURR">-54.6505</ConsValue></ConsEstimate><ConsEstimate type="Median"><ConsValue dateType="CURR">-54.6505</ConsValue></ConsEstimate><ConsEstimate type="StdDev"><ConsValue dateType="CURR">9.5065</ConsValue></ConsEstimate><ConsEstimate type="NumOfEst"><ConsValue dateType="CURR">2</ConsValue></ConsEstimate></FYPeriod></FYEstimate><FYEstimate type="EPS as of Aug31 2019" unit="U"><FYPeriod endCalYear="2011" endMonth="12" fYear="2011" periodType="A"><ConsEstimate type="High"><ConsValue dateType="CURR">0.3500</ConsValue></ConsEstimate><ConsEstimate type="Low"><ConsValue dateType="CURR">0.2620</ConsValue></ConsEstimate><ConsEstimate type="Mean"><ConsValue dateType="CURR">0.3175</ConsValue></ConsEstimate><ConsEstimate type="Median"><ConsValue dateType="CURR">0.3143</ConsValue></ConsEstimate><ConsEstimate type="StdDev"><ConsValue dateType="CURR">0.0218</ConsValue></ConsEstimate><ConsEstimate type="NumOfEst"><ConsValue dateType="CURR">14</ConsValue></ConsEstimate></FYPeriod><FYPeriod endCalYear="2012" endMonth="12" fYear="2012" periodType="A"><ConsEstimate type="High"><ConsValue dateType="CURR">0.3040</ConsValue></ConsEstimate><ConsEstimate type="Low"><ConsValue dateType="CURR">0.0430</ConsValue></ConsEstimate><ConsEstimate type="Mean"><ConsValue dateType="CURR">0.1064</ConsValue></ConsEstimate><ConsEstimate type="Median"><ConsValue dateType="CURR">0.0900</ConsValue></ConsEstimate><ConsEstimate type="StdDev"><ConsValue dateType="CURR">0.0614</ConsValue></ConsEstimate><ConsEstimate type="NumOfEst"><ConsValue dateType="CURR">15</ConsValue></ConsEstimate></FYPeriod><FYPeriod endCalYear="2013" endMonth="12" fYear="2013" periodType="A"><ConsEstimate type="High"><ConsValue dateType="CURR">0.1000</ConsValue></ConsEstimate><ConsEstimate type="Low"><ConsValue dateType="CURR">-0.3200</ConsValue></ConsEstimate><ConsEstimate type="Mean"><ConsValue dateType="CURR">-0.1049</ConsValue></ConsEstimate><ConsEstimate type="Median"><ConsValue dateType="CURR">-0.0590</ConsValue></ConsEstimate><ConsEstimate type="StdDev"><ConsValue dateType="CURR">0.1413</ConsValue></ConsEstimate><ConsEstimate type="NumOfEst"><ConsValue dateType="CURR">7</ConsValue></ConsEstimate></FYPeriod><FYPeriod endCalYear="2013" endMonth="09" fYear="2013" periodNum="3" periodType="Q"><ConsEstimate type="High"><ConsValue dateType="CURR">-0.2000</ConsValue></ConsEstimate><ConsEstimate type="Low"><ConsValue dateType="CURR">-0.2000</ConsValue></ConsEstimate><ConsEstimate type="Mean"><ConsValue dateType="CURR">-0.2000</ConsValue></ConsEstimate><ConsEstimate type="Median"><ConsValue dateType="CURR">-0.2000</ConsValue></ConsEstimate><ConsEstimate type="StdDev"><ConsValue dateType="CURR">0.0000</ConsValue></ConsEstimate><ConsEstimate type="NumOfEst"><ConsValue dateType="CURR">1</ConsValue></ConsEstimate></FYPeriod><FYPeriod endCalYear="2014" endMonth="12" fYear="2014" periodType="A"><ConsEstimate type="High"><ConsValue dateType="CURR">-0.3050</ConsValue></ConsEstimate><ConsEstimate type="Low"><ConsValue dateType="CURR">-0.5380</ConsValue></ConsEstimate><ConsEstimate type="Mean"><ConsValue dateType="CURR">-0.4215</ConsValue></ConsEstimate><ConsEstimate type="Median"><ConsValue dateType="CURR">-0.4215</ConsValue></ConsEstimate><ConsEstimate type="StdDev"><ConsValue dateType="CURR">0.1165</ConsValue></ConsEstimate><ConsEstimate type="NumOfEst"><ConsValue dateType="CURR">2</ConsValue></ConsEstimate></FYPeriod><FYPeriod endCalYear="2014" endMonth="12" fYear="2014" periodNum="4" periodType="Q"><ConsEstimate type="High"><ConsValue dateType="CURR">0.0200</ConsValue></ConsEstimate><ConsEstimate type="Low"><ConsValue dateType="CURR">0.0200</ConsValue></ConsEstimate><ConsEstimate type="Mean"><ConsValue dateType="CURR">0.0200</ConsValue></ConsEstimate><ConsEstimate type="Median"><ConsValue dateType="CURR">0.0200</ConsValue></ConsEstimate><ConsEstimate type="StdDev"><ConsValue dateType="CURR">0.0000</ConsValue></ConsEstimate><ConsEstimate type="NumOfEst"><ConsValue dateType="CURR">1</ConsValue></ConsEstimate></FYPeriod></FYEstimate><FYEstimate type="EPSREP as of Aug31 2019" unit="U"><FYPeriod endCalYear="2011" endMonth="12" fYear="2011" periodType="A"><ConsEstimate type="High"><ConsValue dateType="CURR">0.5200</ConsValue></ConsEstimate><ConsEstimate type="Low"><ConsValue dateType="CURR">0.2620</ConsValue></ConsEstimate><ConsEstimate type="Mean"><ConsValue dateType="CURR">0.3522</ConsValue></ConsEstimate><ConsEstimate type="Median"><ConsValue dateType="CURR">0.3300</ConsValue></ConsEstimate><ConsEstimate type="StdDev"><ConsValue dateType="CURR">0.0756</ConsValue></ConsEstimate><ConsEstimate type="NumOfEst"><ConsValue dateType="CURR">11</ConsValue></ConsEstimate></FYPeriod><FYPeriod endCalYear="2012" endMonth="12" fYear="2012" periodType="A"><ConsEstimate type="High"><ConsValue dateType="CURR">0.5920</ConsValue></ConsEstimate><ConsEstimate type="Low"><ConsValue dateType="CURR">-0.0400</ConsValue></ConsEstimate><ConsEstimate type="Mean"><ConsValue dateType="CURR">0.1223</ConsValue></ConsEstimate><ConsEstimate type="Median"><ConsValue dateType="CURR">0.0800</ConsValue></ConsEstimate><ConsEstimate type="StdDev"><ConsValue dateType="CURR">0.1774</ConsValue></ConsEstimate><ConsEstimate type="NumOfEst"><ConsValue dateType="CURR">9</ConsValue></ConsEstimate></FYPeriod><FYPeriod endCalYear="2013" endMonth="12" fYear="2013" periodType="A"><ConsEstimate type="High"><ConsValue dateType="CURR">-0.0300</ConsValue></ConsEstimate><ConsEstimate type="Low"><ConsValue dateType="CURR">-0.3200</ConsValue></ConsEstimate><ConsEstimate type="Mean"><ConsValue dateType="CURR">-0.1363</ConsValue></ConsEstimate><ConsEstimate type="Median"><ConsValue dateType="CURR">-0.0590</ConsValue></ConsEstimate><ConsEstimate type="StdDev"><ConsValue dateType="CURR">0.1304</ConsValue></ConsEstimate><ConsEstimate type="NumOfEst"><ConsValue dateType="CURR">3</ConsValue></ConsEstimate></FYPeriod><FYPeriod endCalYear="2014" endMonth="12" fYear="2014" periodType="A"><ConsEstimate type="High"><ConsValue dateType="CURR">-0.5380</ConsValue></ConsEstimate><ConsEstimate type="Low"><ConsValue dateType="CURR">-0.5380</ConsValue></ConsEstimate><ConsEstimate type="Mean"><ConsValue dateType="CURR">-0.5380</ConsValue></ConsEstimate><ConsEstimate type="Median"><ConsValue dateType="CURR">-0.5380</ConsValue></ConsEstimate><ConsEstimate type="StdDev"><ConsValue dateType="CURR">0.0000</ConsValue></ConsEstimate><ConsEstimate type="NumOfEst"><ConsValue dateType="CURR">1</ConsValue></ConsEstimate></FYPeriod></FYEstimate><FYEstimate type="NAV as of Aug31 2019" unit="U"><FYPeriod endCalYear="2011" endMonth="12" fYear="2011" periodType="A"><ConsEstimate type="High"><ConsValue dateType="CURR">3.6100</ConsValue></ConsEstimate><ConsEstimate type="Low"><ConsValue dateType="CURR">3.6100</ConsValue></ConsEstimate><ConsEstimate type="Mean"><ConsValue dateType="CURR">3.6100</ConsValue></ConsEstimate><ConsEstimate type="Median"><ConsValue dateType="CURR">3.6100</ConsValue></ConsEstimate><ConsEstimate type="StdDev"><ConsValue dateType="CURR">0.0000</ConsValue></ConsEstimate><ConsEstimate type="NumOfEst"><ConsValue dateType="CURR">1</ConsValue></ConsEstimate></FYPeriod><FYPeriod endCalYear="2012" endMonth="12" fYear="2012" periodType="A"><ConsEstimate type="High"><ConsValue dateType="CURR">3.5800</ConsValue></ConsEstimate><ConsEstimate type="Low"><ConsValue dateType="CURR">3.5800</ConsValue></ConsEstimate><ConsEstimate type="Mean"><ConsValue dateType="CURR">3.5800</ConsValue></ConsEstimate><ConsEstimate type="Median"><ConsValue dateType="CURR">3.5800</ConsValue></ConsEstimate><ConsEstimate type="StdDev"><ConsValue dateType="CURR">0.0000</ConsValue></ConsEstimate><ConsEstimate type="NumOfEst"><ConsValue dateType="CURR">1</ConsValue></ConsEstimate></FYPeriod></FYEstimate><FYEstimate type="NDEBT as of Aug31 2019" unit="M"><FYPeriod endCalYear="2011" endMonth="12" fYear="2011" periodType="A"><ConsEstimate type="High"><ConsValue dateType="CURR">4830.0000</ConsValue></ConsEstimate><ConsEstimate type="Low"><ConsValue dateType="CURR">1649.0000</ConsValue></ConsEstimate><ConsEstimate type="Mean"><ConsValue dateType="CURR">3810.9066</ConsValue></ConsEstimate><ConsEstimate type="Median"><ConsValue dateType="CURR">4513.7295</ConsValue></ConsEstimate><ConsEstimate type="StdDev"><ConsValue dateType="CURR">1142.8205</ConsValue></ConsEstimate><ConsEstimate type="NumOfEst"><ConsValue dateType="CURR">8</ConsValue></ConsEstimate></FYPeriod><FYPeriod endCalYear="2012" endMonth="12" fYear="2012" periodType="A"><ConsEstimate type="High"><ConsValue dateType="CURR">6785.0000</ConsValue></ConsEstimate><ConsEstimate type="Low"><ConsValue dateType="CURR">4445.1770</ConsValue></ConsEstimate><ConsEstimate type="Mean"><ConsValue dateType="CURR">5897.5345</ConsValue></ConsEstimate><ConsEstimate type="Median"><ConsValue dateType="CURR">5855.0000</ConsValue></ConsEstimate><ConsEstimate type="StdDev"><ConsValue dateType="CURR">650.7993</ConsValue></ConsEstimate><ConsEstimate type="NumOfEst"><ConsValue dateType="CURR">9</ConsValue></ConsEstimate></FYPeriod><FYPeriod endCalYear="2013" endMonth="12" fYear="2013" periodType="A"><ConsEstimate type="High"><ConsValue dateType="CURR">6366.2500</ConsValue></ConsEstimate><ConsEstimate type="Low"><ConsValue dateType="CURR">2817.1400</ConsValue></ConsEstimate><ConsEstimate type="Mean"><ConsValue dateType="CURR">4497.3165</ConsValue></ConsEstimate><ConsEstimate type="Median"><ConsValue dateType="CURR">4437.7610</ConsValue></ConsEstimate><ConsEstimate type="StdDev"><ConsValue dateType="CURR">1077.3825</ConsValue></ConsEstimate><ConsEstimate type="NumOfEst"><ConsValue dateType="CURR">6</ConsValue></ConsEstimate></FYPeriod><FYPeriod endCalYear="2014" endMonth="12" fYear="2014" periodType="A"><ConsEstimate type="High"><ConsValue dateType="CURR">6292.6390</ConsValue></ConsEstimate><ConsEstimate type="Low"><ConsValue dateType="CURR">3580.1910</ConsValue></ConsEstimate><ConsEstimate type="Mean"><ConsValue dateType="CURR">4936.4150</ConsValue></ConsEstimate><ConsEstimate type="Median"><ConsValue dateType="CURR">4936.4150</ConsValue></ConsEstimate><ConsEstimate type="StdDev"><ConsValue dateType="CURR">1356.2240</ConsValue></ConsEstimate><ConsEstimate type="NumOfEst"><ConsValue dateType="CURR">2</ConsValue></ConsEstimate></FYPeriod></FYEstimate><FYEstimate type="NPROFIT as of Aug31 2019" unit="M"><FYPeriod endCalYear="2011" endMonth="12" fYear="2011" periodType="A"><ConsEstimate type="High"><ConsValue dateType="CURR">730.1200</ConsValue></ConsEstimate><ConsEstimate type="Low"><ConsValue dateType="CURR">539.0000</ConsValue></ConsEstimate><ConsEstimate type="Mean"><ConsValue dateType="CURR">662.5671</ConsValue></ConsEstimate><ConsEstimate type="Median"><ConsValue dateType="CURR">662.4490</ConsValue></ConsEstimate><ConsEstimate type="StdDev"><ConsValue dateType="CURR">48.0502</ConsValue></ConsEstimate><ConsEstimate type="NumOfEst"><ConsValue dateType="CURR">15</ConsValue></ConsEstimate></FYPeriod><FYPeriod endCalYear="2011" endMonth="12" fYear="2011" periodNum="2" periodType="S"><ConsEstimate type="High"><ConsValue dateType="CURR">374.0000</ConsValue></ConsEstimate><ConsEstimate type="Low"><ConsValue dateType="CURR">374.0000</ConsValue></ConsEstimate><ConsEstimate type="Mean"><ConsValue dateType="CURR">374.0000</ConsValue></ConsEstimate><ConsEstimate type="Median"><ConsValue dateType="CURR">374.0000</ConsValue></ConsEstimate><ConsEstimate type="StdDev"><ConsValue dateType="CURR">0.0000</ConsValue></ConsEstimate><ConsEstimate type="NumOfEst"><ConsValue dateType="CURR">1</ConsValue></ConsEstimate></FYPeriod><FYPeriod endCalYear="2012" endMonth="12" fYear="2012" periodType="A"><ConsEstimate type="High"><ConsValue dateType="CURR">305.0000</ConsValue></ConsEstimate><ConsEstimate type="Low"><ConsValue dateType="CURR">87.8650</ConsValue></ConsEstimate><ConsEstimate type="Mean"><ConsValue dateType="CURR">182.6147</ConsValue></ConsEstimate><ConsEstimate type="Median"><ConsValue dateType="CURR">183.1750</ConsValue></ConsEstimate><ConsEstimate type="StdDev"><ConsValue dateType="CURR">66.8741</ConsValue></ConsEstimate><ConsEstimate type="NumOfEst"><ConsValue dateType="CURR">14</ConsValue></ConsEstimate></FYPeriod><FYPeriod endCalYear="2012" endMonth="06" fYear="2012" periodNum="1" periodType="S"><ConsEstimate type="High"><ConsValue dateType="CURR">258.0000</ConsValue></ConsEstimate><ConsEstimate type="Low"><ConsValue dateType="CURR">258.0000</ConsValue></ConsEstimate><ConsEstimate type="Mean"><ConsValue dateType="CURR">258.0000</ConsValue></ConsEstimate><ConsEstimate type="Median"><ConsValue dateType="CURR">258.0000</ConsValue></ConsEstimate><ConsEstimate type="StdDev"><ConsValue dateType="CURR">0.0000</ConsValue></ConsEstimate><ConsEstimate type="NumOfEst"><ConsValue dateType="CURR">1</ConsValue></ConsEstimate></FYPeriod><FYPeriod endCalYear="2013" endMonth="12" fYear="2013" periodType="A"><ConsEstimate type="High"><ConsValue dateType="CURR">200.0000</ConsValue></ConsEstimate><ConsEstimate type="Low"><ConsValue dateType="CURR">-659.0000</ConsValue></ConsEstimate><ConsEstimate type="Mean"><ConsValue dateType="CURR">-229.6823</ConsValue></ConsEstimate><ConsEstimate type="Median"><ConsValue dateType="CURR">-174.0000</ConsValue></ConsEstimate><ConsEstimate type="StdDev"><ConsValue dateType="CURR">279.4363</ConsValue></ConsEstimate><ConsEstimate type="NumOfEst"><ConsValue dateType="CURR">7</ConsValue></ConsEstimate></FYPeriod><FYPeriod endCalYear="2013" endMonth="09" fYear="2013" periodNum="3" periodType="Q"><ConsEstimate type="High"><ConsValue dateType="CURR">-410.0000</ConsValue></ConsEstimate><ConsEstimate type="Low"><ConsValue dateType="CURR">-410.0000</ConsValue></ConsEstimate><ConsEstimate type="Mean"><ConsValue dateType="CURR">-410.0000</ConsValue></ConsEstimate><ConsEstimate type="Median"><ConsValue dateType="CURR">-410.0000</ConsValue></ConsEstimate><ConsEstimate type="StdDev"><ConsValue dateType="CURR">0.0000</ConsValue></ConsEstimate><ConsEstimate type="NumOfEst"><ConsValue dateType="CURR">1</ConsValue></ConsEstimate></FYPeriod><FYPeriod endCalYear="2013" endMonth="12" fYear="2013" periodNum="4" periodType="Q"><ConsEstimate type="High"><ConsValue dateType="CURR">95.0000</ConsValue></ConsEstimate><ConsEstimate type="Low"><ConsValue dateType="CURR">95.0000</ConsValue></ConsEstimate><ConsEstimate type="Mean"><ConsValue dateType="CURR">95.0000</ConsValue></ConsEstimate><ConsEstimate type="Median"><ConsValue dateType="CURR">95.0000</ConsValue></ConsEstimate><ConsEstimate type="StdDev"><ConsValue dateType="CURR">0.0000</ConsValue></ConsEstimate><ConsEstimate type="NumOfEst"><ConsValue dateType="CURR">1</ConsValue></ConsEstimate></FYPeriod><FYPeriod endCalYear="2014" endMonth="12" fYear="2014" periodType="A"><ConsEstimate type="High"><ConsValue dateType="CURR">-628.8850</ConsValue></ConsEstimate><ConsEstimate type="Low"><ConsValue dateType="CURR">-1103.0790</ConsValue></ConsEstimate><ConsEstimate type="Mean"><ConsValue dateType="CURR">-865.9820</ConsValue></ConsEstimate><ConsEstimate type="Median"><ConsValue dateType="CURR">-865.9820</ConsValue></ConsEstimate><ConsEstimate type="StdDev"><ConsValue dateType="CURR">237.0970</ConsValue></ConsEstimate><ConsEstimate type="NumOfEst"><ConsValue dateType="CURR">2</ConsValue></ConsEstimate></FYPeriod></FYEstimate><FYEstimate type="NPROFITREP as of Aug31 2019" unit="M"><FYPeriod endCalYear="2011" endMonth="12" fYear="2011" periodType="A"><ConsEstimate type="High"><ConsValue dateType="CURR">1085.0000</ConsValue></ConsEstimate><ConsEstimate type="Low"><ConsValue dateType="CURR">539.0000</ConsValue></ConsEstimate><ConsEstimate type="Mean"><ConsValue dateType="CURR">698.3637</ConsValue></ConsEstimate><ConsEstimate type="Median"><ConsValue dateType="CURR">646.0000</ConsValue></ConsEstimate><ConsEstimate type="StdDev"><ConsValue dateType="CURR">145.7012</ConsValue></ConsEstimate><ConsEstimate type="NumOfEst"><ConsValue dateType="CURR">9</ConsValue></ConsEstimate></FYPeriod><FYPeriod endCalYear="2011" endMonth="12" fYear="2011" periodNum="2" periodType="S"><ConsEstimate type="High"><ConsValue dateType="CURR">374.0000</ConsValue></ConsEstimate><ConsEstimate type="Low"><ConsValue dateType="CURR">374.0000</ConsValue></ConsEstimate><ConsEstimate type="Mean"><ConsValue dateType="CURR">374.0000</ConsValue></ConsEstimate><ConsEstimate type="Median"><ConsValue dateType="CURR">374.0000</ConsValue></ConsEstimate><ConsEstimate type="StdDev"><ConsValue dateType="CURR">0.0000</ConsValue></ConsEstimate><ConsEstimate type="NumOfEst"><ConsValue dateType="CURR">1</ConsValue></ConsEstimate></FYPeriod><FYPeriod endCalYear="2012" endMonth="12" fYear="2012" periodType="A"><ConsEstimate type="High"><ConsValue dateType="CURR">305.0000</ConsValue></ConsEstimate><ConsEstimate type="Low"><ConsValue dateType="CURR">-85.0000</ConsValue></ConsEstimate><ConsEstimate type="Mean"><ConsValue dateType="CURR">158.8620</ConsValue></ConsEstimate><ConsEstimate type="Median"><ConsValue dateType="CURR">174.0000</ConsValue></ConsEstimate><ConsEstimate type="StdDev"><ConsValue dateType="CURR">123.6967</ConsValue></ConsEstimate><ConsEstimate type="NumOfEst"><ConsValue dateType="CURR">7</ConsValue></ConsEstimate></FYPeriod><FYPeriod endCalYear="2012" endMonth="06" fYear="2012" periodNum="1" periodType="S"><ConsEstimate type="High"><ConsValue dateType="CURR">258.0000</ConsValue></ConsEstimate><ConsEstimate type="Low"><ConsValue dateType="CURR">258.0000</ConsValue></ConsEstimate><ConsEstimate type="Mean"><ConsValue dateType="CURR">258.0000</ConsValue></ConsEstimate><ConsEstimate type="Median"><ConsValue dateType="CURR">258.0000</ConsValue></ConsEstimate><ConsEstimate type="StdDev"><ConsValue dateType="CURR">0.0000</ConsValue></ConsEstimate><ConsEstimate type="NumOfEst"><ConsValue dateType="CURR">1</ConsValue></ConsEstimate></FYPeriod><FYPeriod endCalYear="2013" endMonth="12" fYear="2013" periodType="A"><ConsEstimate type="High"><ConsValue dateType="CURR">-120.7470</ConsValue></ConsEstimate><ConsEstimate type="Low"><ConsValue dateType="CURR">-659.0000</ConsValue></ConsEstimate><ConsEstimate type="Mean"><ConsValue dateType="CURR">-317.9157</ConsValue></ConsEstimate><ConsEstimate type="Median"><ConsValue dateType="CURR">-174.0000</ConsValue></ConsEstimate><ConsEstimate type="StdDev"><ConsValue dateType="CURR">242.1609</ConsValue></ConsEstimate><ConsEstimate type="NumOfEst"><ConsValue dateType="CURR">3</ConsValue></ConsEstimate></FYPeriod><FYPeriod endCalYear="2013" endMonth="12" fYear="2013" periodNum="4" periodType="Q"><ConsEstimate type="High"><ConsValue dateType="CURR">95.0000</ConsValue></ConsEstimate><ConsEstimate type="Low"><ConsValue dateType="CURR">95.0000</ConsValue></ConsEstimate><ConsEstimate type="Mean"><ConsValue dateType="CURR">95.0000</ConsValue></ConsEstimate><ConsEstimate type="Median"><ConsValue dateType="CURR">95.0000</ConsValue></ConsEstimate><ConsEstimate type="StdDev"><ConsValue dateType="CURR">0.0000</ConsValue></ConsEstimate><ConsEstimate type="NumOfEst"><ConsValue dateType="CURR">1</ConsValue></ConsEstimate></FYPeriod><FYPeriod endCalYear="2014" endMonth="12" fYear="2014" periodType="A"><ConsEstimate type="High"><ConsValue dateType="CURR">-1103.0790</ConsValue></ConsEstimate><ConsEstimate type="Low"><ConsValue dateType="CURR">-1103.0790</ConsValue></ConsEstimate><ConsEstimate type="Mean"><ConsValue dateType="CURR">-1103.0790</ConsValue></ConsEstimate><ConsEstimate type="Median"><ConsValue dateType="CURR">-1103.0790</ConsValue></ConsEstimate><ConsEstimate type="StdDev"><ConsValue dateType="CURR">0.0000</ConsValue></ConsEstimate><ConsEstimate type="NumOfEst"><ConsValue dateType="CURR">1</ConsValue></ConsEstimate></FYPeriod></FYEstimate><FYEstimate type="OPROFIT as of Aug31 2019" unit="M"><FYPeriod endCalYear="2011" endMonth="12" fYear="2011" periodType="A"><ConsEstimate type="High"><ConsValue dateType="CURR">1267.2670</ConsValue></ConsEstimate><ConsEstimate type="Low"><ConsValue dateType="CURR">1028.8064</ConsValue></ConsEstimate><ConsEstimate type="Mean"><ConsValue dateType="CURR">1170.4812</ConsValue></ConsEstimate><ConsEstimate type="Median"><ConsValue dateType="CURR">1165.6200</ConsValue></ConsEstimate><ConsEstimate type="StdDev"><ConsValue dateType="CURR">78.1224</ConsValue></ConsEstimate><ConsEstimate type="NumOfEst"><ConsValue dateType="CURR">7</ConsValue></ConsEstimate></FYPeriod><FYPeriod endCalYear="2012" endMonth="12" fYear="2012" periodType="A"><ConsEstimate type="High"><ConsValue dateType="CURR">638.0910</ConsValue></ConsEstimate><ConsEstimate type="Low"><ConsValue dateType="CURR">638.0910</ConsValue></ConsEstimate><ConsEstimate type="Mean"><ConsValue dateType="CURR">638.0910</ConsValue></ConsEstimate><ConsEstimate type="Median"><ConsValue dateType="CURR">638.0910</ConsValue></ConsEstimate><ConsEstimate type="StdDev"><ConsValue dateType="CURR">0.0000</ConsValue></ConsEstimate><ConsEstimate type="NumOfEst"><ConsValue dateType="CURR">1</ConsValue></ConsEstimate></FYPeriod><FYPeriod endCalYear="2013" endMonth="12" fYear="2013" periodType="A"><ConsEstimate type="High"><ConsValue dateType="CURR">-69.2080</ConsValue></ConsEstimate><ConsEstimate type="Low"><ConsValue dateType="CURR">-69.2080</ConsValue></ConsEstimate><ConsEstimate type="Mean"><ConsValue dateType="CURR">-69.2080</ConsValue></ConsEstimate><ConsEstimate type="Median"><ConsValue dateType="CURR">-69.2080</ConsValue></ConsEstimate><ConsEstimate type="StdDev"><ConsValue dateType="CURR">0.0000</ConsValue></ConsEstimate><ConsEstimate type="NumOfEst"><ConsValue dateType="CURR">1</ConsValue></ConsEstimate></FYPeriod><FYPeriod endCalYear="2014" endMonth="12" fYear="2014" periodType="A"><ConsEstimate type="High"><ConsValue dateType="CURR">-140.5210</ConsValue></ConsEstimate><ConsEstimate type="Low"><ConsValue dateType="CURR">-140.5210</ConsValue></ConsEstimate><ConsEstimate type="Mean"><ConsValue dateType="CURR">-140.5210</ConsValue></ConsEstimate><ConsEstimate type="Median"><ConsValue dateType="CURR">-140.5210</ConsValue></ConsEstimate><ConsEstimate type="StdDev"><ConsValue dateType="CURR">0.0000</ConsValue></ConsEstimate><ConsEstimate type="NumOfEst"><ConsValue dateType="CURR">1</ConsValue></ConsEstimate></FYPeriod></FYEstimate><FYEstimate type="PPROFIT as of Aug31 2019" unit="M"><FYPeriod endCalYear="2011" endMonth="12" fYear="2011" periodType="A"><ConsEstimate type="High"><ConsValue dateType="CURR">1041.0000</ConsValue></ConsEstimate><ConsEstimate type="Low"><ConsValue dateType="CURR">689.0000</ConsValue></ConsEstimate><ConsEstimate type="Mean"><ConsValue dateType="CURR">863.0244</ConsValue></ConsEstimate><ConsEstimate type="Median"><ConsValue dateType="CURR">851.8390</ConsValue></ConsEstimate><ConsEstimate type="StdDev"><ConsValue dateType="CURR">80.0444</ConsValue></ConsEstimate><ConsEstimate type="NumOfEst"><ConsValue dateType="CURR">13</ConsValue></ConsEstimate></FYPeriod><FYPeriod endCalYear="2011" endMonth="12" fYear="2011" periodNum="2" periodType="S"><ConsEstimate type="High"><ConsValue dateType="CURR">512.0000</ConsValue></ConsEstimate><ConsEstimate type="Low"><ConsValue dateType="CURR">512.0000</ConsValue></ConsEstimate><ConsEstimate type="Mean"><ConsValue dateType="CURR">512.0000</ConsValue></ConsEstimate><ConsEstimate type="Median"><ConsValue dateType="CURR">512.0000</ConsValue></ConsEstimate><ConsEstimate type="StdDev"><ConsValue dateType="CURR">0.0000</ConsValue></ConsEstimate><ConsEstimate type="NumOfEst"><ConsValue dateType="CURR">1</ConsValue></ConsEstimate></FYPeriod><FYPeriod endCalYear="2012" endMonth="12" fYear="2012" periodType="A"><ConsEstimate type="High"><ConsValue dateType="CURR">430.0000</ConsValue></ConsEstimate><ConsEstimate type="Low"><ConsValue dateType="CURR">-76.5600</ConsValue></ConsEstimate><ConsEstimate type="Mean"><ConsValue dateType="CURR">260.1130</ConsValue></ConsEstimate><ConsEstimate type="Median"><ConsValue dateType="CURR">277.2590</ConsValue></ConsEstimate><ConsEstimate type="StdDev"><ConsValue dateType="CURR">134.4302</ConsValue></ConsEstimate><ConsEstimate type="NumOfEst"><ConsValue dateType="CURR">11</ConsValue></ConsEstimate></FYPeriod><FYPeriod endCalYear="2012" endMonth="06" fYear="2012" periodNum="1" periodType="S"><ConsEstimate type="High"><ConsValue dateType="CURR">346.0000</ConsValue></ConsEstimate><ConsEstimate type="Low"><ConsValue dateType="CURR">346.0000</ConsValue></ConsEstimate><ConsEstimate type="Mean"><ConsValue dateType="CURR">346.0000</ConsValue></ConsEstimate><ConsEstimate type="Median"><ConsValue dateType="CURR">346.0000</ConsValue></ConsEstimate><ConsEstimate type="StdDev"><ConsValue dateType="CURR">0.0000</ConsValue></ConsEstimate><ConsEstimate type="NumOfEst"><ConsValue dateType="CURR">1</ConsValue></ConsEstimate></FYPeriod><FYPeriod endCalYear="2013" endMonth="12" fYear="2013" periodType="A"><ConsEstimate type="High"><ConsValue dateType="CURR">-58.7310</ConsValue></ConsEstimate><ConsEstimate type="Low"><ConsValue dateType="CURR">-654.0000</ConsValue></ConsEstimate><ConsEstimate type="Mean"><ConsValue dateType="CURR">-208.7560</ConsValue></ConsEstimate><ConsEstimate type="Median"><ConsValue dateType="CURR">-95.0000</ConsValue></ConsEstimate><ConsEstimate type="StdDev"><ConsValue dateType="CURR">224.7073</ConsValue></ConsEstimate><ConsEstimate type="NumOfEst"><ConsValue dateType="CURR">5</ConsValue></ConsEstimate></FYPeriod><FYPeriod endCalYear="2014" endMonth="12" fYear="2014" periodType="A"><ConsEstimate type="High"><ConsValue dateType="CURR">-834.0540</ConsValue></ConsEstimate><ConsEstimate type="Low"><ConsValue dateType="CURR">-1312.1540</ConsValue></ConsEstimate><ConsEstimate type="Mean"><ConsValue dateType="CURR">-1073.1040</ConsValue></ConsEstimate><ConsEstimate type="Median"><ConsValue dateType="CURR">-1073.1040</ConsValue></ConsEstimate><ConsEstimate type="StdDev"><ConsValue dateType="CURR">239.0500</ConsValue></ConsEstimate><ConsEstimate type="NumOfEst"><ConsValue dateType="CURR">2</ConsValue></ConsEstimate></FYPeriod></FYEstimate><FYEstimate type="PPROFITREP as of Aug31 2019" unit="M"><FYPeriod endCalYear="2011" endMonth="12" fYear="2011" periodType="A"><ConsEstimate type="High"><ConsValue dateType="CURR">1275.0000</ConsValue></ConsEstimate><ConsEstimate type="Low"><ConsValue dateType="CURR">689.0000</ConsValue></ConsEstimate><ConsEstimate type="Mean"><ConsValue dateType="CURR">910.2421</ConsValue></ConsEstimate><ConsEstimate type="Median"><ConsValue dateType="CURR">879.0000</ConsValue></ConsEstimate><ConsEstimate type="StdDev"><ConsValue dateType="CURR">156.9707</ConsValue></ConsEstimate><ConsEstimate type="NumOfEst"><ConsValue dateType="CURR">9</ConsValue></ConsEstimate></FYPeriod><FYPeriod endCalYear="2011" endMonth="12" fYear="2011" periodNum="2" periodType="S"><ConsEstimate type="High"><ConsValue dateType="CURR">512.0000</ConsValue></ConsEstimate><ConsEstimate type="Low"><ConsValue dateType="CURR">512.0000</ConsValue></ConsEstimate><ConsEstimate type="Mean"><ConsValue dateType="CURR">512.0000</ConsValue></ConsEstimate><ConsEstimate type="Median"><ConsValue dateType="CURR">512.0000</ConsValue></ConsEstimate><ConsEstimate type="StdDev"><ConsValue dateType="CURR">0.0000</ConsValue></ConsEstimate><ConsEstimate type="NumOfEst"><ConsValue dateType="CURR">1</ConsValue></ConsEstimate></FYPeriod><FYPeriod endCalYear="2012" endMonth="12" fYear="2012" periodType="A"><ConsEstimate type="High"><ConsValue dateType="CURR">430.0000</ConsValue></ConsEstimate><ConsEstimate type="Low"><ConsValue dateType="CURR">-112.0000</ConsValue></ConsEstimate><ConsEstimate type="Mean"><ConsValue dateType="CURR">231.9546</ConsValue></ConsEstimate><ConsEstimate type="Median"><ConsValue dateType="CURR">266.0000</ConsValue></ConsEstimate><ConsEstimate type="StdDev"><ConsValue dateType="CURR">197.3657</ConsValue></ConsEstimate><ConsEstimate type="NumOfEst"><ConsValue dateType="CURR">5</ConsValue></ConsEstimate></FYPeriod><FYPeriod endCalYear="2012" endMonth="06" fYear="2012" periodNum="1" periodType="S"><ConsEstimate type="High"><ConsValue dateType="CURR">346.0000</ConsValue></ConsEstimate><ConsEstimate type="Low"><ConsValue dateType="CURR">346.0000</ConsValue></ConsEstimate><ConsEstimate type="Mean"><ConsValue dateType="CURR">346.0000</ConsValue></ConsEstimate><ConsEstimate type="Median"><ConsValue dateType="CURR">346.0000</ConsValue></ConsEstimate><ConsEstimate type="StdDev"><ConsValue dateType="CURR">0.0000</ConsValue></ConsEstimate><ConsEstimate type="NumOfEst"><ConsValue dateType="CURR">1</ConsValue></ConsEstimate></FYPeriod><FYPeriod endCalYear="2013" endMonth="12" fYear="2013" periodType="A"><ConsEstimate type="High"><ConsValue dateType="CURR">-95.0000</ConsValue></ConsEstimate><ConsEstimate type="Low"><ConsValue dateType="CURR">-654.0000</ConsValue></ConsEstimate><ConsEstimate type="Mean"><ConsValue dateType="CURR">-374.5000</ConsValue></ConsEstimate><ConsEstimate type="Median"><ConsValue dateType="CURR">-374.5000</ConsValue></ConsEstimate><ConsEstimate type="StdDev"><ConsValue dateType="CURR">279.5000</ConsValue></ConsEstimate><ConsEstimate type="NumOfEst"><ConsValue dateType="CURR">2</ConsValue></ConsEstimate></FYPeriod></FYEstimate><FYEstimate type="REVENUE as of Aug31 2019" unit="M"><FYPeriod endCalYear="2011" endMonth="12" fYear="2011" periodType="A"><ConsEstimate type="High"><ConsValue dateType="CURR">2973.0000</ConsValue></ConsEstimate><ConsEstimate type="Low"><ConsValue dateType="CURR">2528.0000</ConsValue></ConsEstimate><ConsEstimate type="Mean"><ConsValue dateType="CURR">2771.7733</ConsValue></ConsEstimate><ConsEstimate type="Median"><ConsValue dateType="CURR">2796.2000</ConsValue></ConsEstimate><ConsEstimate type="StdDev"><ConsValue dateType="CURR">130.2774</ConsValue></ConsEstimate><ConsEstimate type="NumOfEst"><ConsValue dateType="CURR">15</ConsValue></ConsEstimate></FYPeriod><FYPeriod endCalYear="2011" endMonth="12" fYear="2011" periodNum="2" periodType="S"><ConsEstimate type="High"><ConsValue dateType="CURR">1650.0000</ConsValue></ConsEstimate><ConsEstimate type="Low"><ConsValue dateType="CURR">1650.0000</ConsValue></ConsEstimate><ConsEstimate type="Mean"><ConsValue dateType="CURR">1650.0000</ConsValue></ConsEstimate><ConsEstimate type="Median"><ConsValue dateType="CURR">1650.0000</ConsValue></ConsEstimate><ConsEstimate type="StdDev"><ConsValue dateType="CURR">0.0000</ConsValue></ConsEstimate><ConsEstimate type="NumOfEst"><ConsValue dateType="CURR">1</ConsValue></ConsEstimate></FYPeriod><FYPeriod endCalYear="2012" endMonth="12" fYear="2012" periodType="A"><ConsEstimate type="High"><ConsValue dateType="CURR">2499.0000</ConsValue></ConsEstimate><ConsEstimate type="Low"><ConsValue dateType="CURR">1811.0000</ConsValue></ConsEstimate><ConsEstimate type="Mean"><ConsValue dateType="CURR">2091.2546</ConsValue></ConsEstimate><ConsEstimate type="Median"><ConsValue dateType="CURR">2075.8885</ConsValue></ConsEstimate><ConsEstimate type="StdDev"><ConsValue dateType="CURR">188.4016</ConsValue></ConsEstimate><ConsEstimate type="NumOfEst"><ConsValue dateType="CURR">15</ConsValue></ConsEstimate></FYPeriod><FYPeriod endCalYear="2012" endMonth="03" fYear="2012" periodNum="1" periodType="Q"><ConsEstimate type="High"><ConsValue dateType="CURR">77.0000</ConsValue></ConsEstimate><ConsEstimate type="Low"><ConsValue dateType="CURR">77.0000</ConsValue></ConsEstimate><ConsEstimate type="Mean"><ConsValue dateType="CURR">77.0000</ConsValue></ConsEstimate><ConsEstimate type="Median"><ConsValue dateType="CURR">77.0000</ConsValue></ConsEstimate><ConsEstimate type="StdDev"><ConsValue dateType="CURR">0.0000</ConsValue></ConsEstimate><ConsEstimate type="NumOfEst"><ConsValue dateType="CURR">1</ConsValue></ConsEstimate></FYPeriod><FYPeriod endCalYear="2012" endMonth="06" fYear="2012" periodNum="2" periodType="Q"><ConsEstimate type="High"><ConsValue dateType="CURR">102.0000</ConsValue></ConsEstimate><ConsEstimate type="Low"><ConsValue dateType="CURR">102.0000</ConsValue></ConsEstimate><ConsEstimate type="Mean"><ConsValue dateType="CURR">102.0000</ConsValue></ConsEstimate><ConsEstimate type="Median"><ConsValue dateType="CURR">102.0000</ConsValue></ConsEstimate><ConsEstimate type="StdDev"><ConsValue dateType="CURR">0.0000</ConsValue></ConsEstimate><ConsEstimate type="NumOfEst"><ConsValue dateType="CURR">1</ConsValue></ConsEstimate></FYPeriod><FYPeriod endCalYear="2012" endMonth="06" fYear="2012" periodNum="1" periodType="S"><ConsEstimate type="High"><ConsValue dateType="CURR">1290.0000</ConsValue></ConsEstimate><ConsEstimate type="Low"><ConsValue dateType="CURR">1290.0000</ConsValue></ConsEstimate><ConsEstimate type="Mean"><ConsValue dateType="CURR">1290.0000</ConsValue></ConsEstimate><ConsEstimate type="Median"><ConsValue dateType="CURR">1290.0000</ConsValue></ConsEstimate><ConsEstimate type="StdDev"><ConsValue dateType="CURR">0.0000</ConsValue></ConsEstimate><ConsEstimate type="NumOfEst"><ConsValue dateType="CURR">1</ConsValue></ConsEstimate></FYPeriod><FYPeriod endCalYear="2013" endMonth="12" fYear="2013" periodType="A"><ConsEstimate type="High"><ConsValue dateType="CURR">2021.0000</ConsValue></ConsEstimate><ConsEstimate type="Low"><ConsValue dateType="CURR">589.4320</ConsValue></ConsEstimate><ConsEstimate type="Mean"><ConsValue dateType="CURR">1041.2801</ConsValue></ConsEstimate><ConsEstimate type="Median"><ConsValue dateType="CURR">867.7880</ConsValue></ConsEstimate><ConsEstimate type="StdDev"><ConsValue dateType="CURR">484.9035</ConsValue></ConsEstimate><ConsEstimate type="NumOfEst"><ConsValue dateType="CURR">7</ConsValue></ConsEstimate></FYPeriod><FYPeriod endCalYear="2014" endMonth="12" fYear="2014" periodType="A"><ConsEstimate type="High"><ConsValue dateType="CURR">693.3070</ConsValue></ConsEstimate><ConsEstimate type="Low"><ConsValue dateType="CURR">642.7800</ConsValue></ConsEstimate><ConsEstimate type="Mean"><ConsValue dateType="CURR">668.0435</ConsValue></ConsEstimate><ConsEstimate type="Median"><ConsValue dateType="CURR">668.0435</ConsValue></ConsEstimate><ConsEstimate type="StdDev"><ConsValue dateType="CURR">25.2635</ConsValue></ConsEstimate><ConsEstimate type="NumOfEst"><ConsValue dateType="CURR">2</ConsValue></ConsEstimate></FYPeriod></FYEstimate><FYEstimate type="ROA as of Aug31 2019" unit="P"><FYPeriod endCalYear="2011" endMonth="12" fYear="2011" periodType="A"><ConsEstimate type="High"><ConsValue dateType="CURR">6.0000</ConsValue></ConsEstimate><ConsEstimate type="Low"><ConsValue dateType="CURR">3.6000</ConsValue></ConsEstimate><ConsEstimate type="Mean"><ConsValue dateType="CURR">4.6143</ConsValue></ConsEstimate><ConsEstimate type="Median"><ConsValue dateType="CURR">4.5300</ConsValue></ConsEstimate><ConsEstimate type="StdDev"><ConsValue dateType="CURR">0.6329</ConsValue></ConsEstimate><ConsEstimate type="NumOfEst"><ConsValue dateType="CURR">8</ConsValue></ConsEstimate></FYPeriod><FYPeriod endCalYear="2012" endMonth="12" fYear="2012" periodType="A"><ConsEstimate type="High"><ConsValue dateType="CURR">2.7070</ConsValue></ConsEstimate><ConsEstimate type="Low"><ConsValue dateType="CURR">0.6310</ConsValue></ConsEstimate><ConsEstimate type="Mean"><ConsValue dateType="CURR">1.3263</ConsValue></ConsEstimate><ConsEstimate type="Median"><ConsValue dateType="CURR">1.0350</ConsValue></ConsEstimate><ConsEstimate type="StdDev"><ConsValue dateType="CURR">0.7623</ConsValue></ConsEstimate><ConsEstimate type="NumOfEst"><ConsValue dateType="CURR">6</ConsValue></ConsEstimate></FYPeriod><FYPeriod endCalYear="2013" endMonth="12" fYear="2013" periodType="A"><ConsEstimate type="High"><ConsValue dateType="CURR">-0.3470</ConsValue></ConsEstimate><ConsEstimate type="Low"><ConsValue dateType="CURR">-0.8990</ConsValue></ConsEstimate><ConsEstimate type="Mean"><ConsValue dateType="CURR">-0.5487</ConsValue></ConsEstimate><ConsEstimate type="Median"><ConsValue dateType="CURR">-0.4000</ConsValue></ConsEstimate><ConsEstimate type="StdDev"><ConsValue dateType="CURR">0.2487</ConsValue></ConsEstimate><ConsEstimate type="NumOfEst"><ConsValue dateType="CURR">3</ConsValue></ConsEstimate></FYPeriod><FYPeriod endCalYear="2014" endMonth="12" fYear="2014" periodType="A"><ConsEstimate type="High"><ConsValue dateType="CURR">-0.8090</ConsValue></ConsEstimate><ConsEstimate type="Low"><ConsValue dateType="CURR">-0.8090</ConsValue></ConsEstimate><ConsEstimate type="Mean"><ConsValue dateType="CURR">-0.8090</ConsValue></ConsEstimate><ConsEstimate type="Median"><ConsValue dateType="CURR">-0.8090</ConsValue></ConsEstimate><ConsEstimate type="StdDev"><ConsValue dateType="CURR">0.0000</ConsValue></ConsEstimate><ConsEstimate type="NumOfEst"><ConsValue dateType="CURR">1</ConsValue></ConsEstimate></FYPeriod></FYEstimate><FYEstimate type="ROE as of Aug31 2019" unit="P"><FYPeriod endCalYear="2011" endMonth="12" fYear="2011" periodType="A"><ConsEstimate type="High"><ConsValue dateType="CURR">10.0400</ConsValue></ConsEstimate><ConsEstimate type="Low"><ConsValue dateType="CURR">6.1000</ConsValue></ConsEstimate><ConsEstimate type="Mean"><ConsValue dateType="CURR">8.7352</ConsValue></ConsEstimate><ConsEstimate type="Median"><ConsValue dateType="CURR">8.7495</ConsValue></ConsEstimate><ConsEstimate type="StdDev"><ConsValue dateType="CURR">1.0517</ConsValue></ConsEstimate><ConsEstimate type="NumOfEst"><ConsValue dateType="CURR">12</ConsValue></ConsEstimate></FYPeriod><FYPeriod endCalYear="2012" endMonth="12" fYear="2012" periodType="A"><ConsEstimate type="High"><ConsValue dateType="CURR">4.0000</ConsValue></ConsEstimate><ConsEstimate type="Low"><ConsValue dateType="CURR">-1.1000</ConsValue></ConsEstimate><ConsEstimate type="Mean"><ConsValue dateType="CURR">1.9508</ConsValue></ConsEstimate><ConsEstimate type="Median"><ConsValue dateType="CURR">2.4055</ConsValue></ConsEstimate><ConsEstimate type="StdDev"><ConsValue dateType="CURR">1.4558</ConsValue></ConsEstimate><ConsEstimate type="NumOfEst"><ConsValue dateType="CURR">14</ConsValue></ConsEstimate></FYPeriod><FYPeriod endCalYear="2013" endMonth="12" fYear="2013" periodType="A"><ConsEstimate type="High"><ConsValue dateType="CURR">2.7000</ConsValue></ConsEstimate><ConsEstimate type="Low"><ConsValue dateType="CURR">-10.6000</ConsValue></ConsEstimate><ConsEstimate type="Mean"><ConsValue dateType="CURR">-3.2226</ConsValue></ConsEstimate><ConsEstimate type="Median"><ConsValue dateType="CURR">-1.6710</ConsValue></ConsEstimate><ConsEstimate type="StdDev"><ConsValue dateType="CURR">4.3272</ConsValue></ConsEstimate><ConsEstimate type="NumOfEst"><ConsValue dateType="CURR">7</ConsValue></ConsEstimate></FYPeriod><FYPeriod endCalYear="2014" endMonth="12" fYear="2014" periodType="A"><ConsEstimate type="High"><ConsValue dateType="CURR">-9.3790</ConsValue></ConsEstimate><ConsEstimate type="Low"><ConsValue dateType="CURR">-17.1550</ConsValue></ConsEstimate><ConsEstimate type="Mean"><ConsValue dateType="CURR">-13.2670</ConsValue></ConsEstimate><ConsEstimate type="Median"><ConsValue dateType="CURR">-13.2670</ConsValue></ConsEstimate><ConsEstimate type="StdDev"><ConsValue dateType="CURR">3.8880</ConsValue></ConsEstimate><ConsEstimate type="NumOfEst"><ConsValue dateType="CURR">2</ConsValue></ConsEstimate></FYPeriod></FYEstimate></FYEstimates><NPEstimates /><Recommendations><STOpinion /></Recommendations></ConsEstimates></REarnEstCons>