<?xml version="1.0" encoding="utf-8"?><REarnEstCons><Company><CoName><Name type="Long">Zhong Ao Home Group Ltd</Name></CoName><CoIds><CoId type="CoId">GL_71157</CoId><CoId type="RepNo">F9020</CoId><CoId type="IssueId">1</CoId><CoId type="IssuerID">206911</CoId><CoId type="RedIssueID">74967</CoId><CoId type="IsPrimaryIssue">1</CoId></CoIds><SecurityInfo><Security code="1"><Exchange code="HKG">Hong Kong Stock Exchange</Exchange><Country set="MX" code="HKG">Hong Kong</Country><SecIds><SecId set="LOCAL" type="RIC">1538.HK</SecId><SecId set="LOCAL" type="Display RIC">1538.HK</SecId><SecId set="LOCAL" type="TICKER">1538</SecId><SecId set="LOCAL" type="ISIN">KYG9897C1033</SecId><SecId set="LOCAL" type="SEDOL">BD614X8</SecId><SecId set="LOCAL" type="CUSIP">G9897C103</SecId></SecIds><MarketData><MarketDataItem type="CLPRICE" currCode="HKD" unit="U" updated="2019-08-29T00:00:00">0.650000</MarketDataItem><MarketDataItem type="SHARESOUT" currCode="HKD" unit="U">817622000</MarketDataItem><MarketDataItem type="MARKETCAP" currCode="HKD" unit="M">531.4543</MarketDataItem><MarketDataItem type="52WKHIGH" currCode="HKD" unit="U" updated="2018-08-30T00:00:00">1.1400</MarketDataItem><MarketDataItem type="52WKLOW" currCode="HKD" unit="U" updated="2019-08-29T00:00:00">0.5800</MarketDataItem></MarketData></Security></SecurityInfo><CompanyInfo><Sector set="MX" code="SERVIC">Services</Sector><Industry set="MX" code="REOPER">Real Estate Operations</Industry><Primary type="Earnings">REP</Primary><Primary type="Consensus">Mean</Primary><Primary type="Estimate">EPS</Primary><Primary type="Periodicity">Q</Primary><Currency set="ISO" type="CONSENSUS" code="HKD">Hong Kong Dollars</Currency><CurFiscalPeriod fYear="2017" fyem="12" periodType="Q" periodNum="3" /><CompanyPeriods><Annual fyNum="-2" fYear="2014" endMonth="12" periodUnit="MNS" periodLength="12"><Interim type="Q" periodNum="1" endMonth="3" endCalYear="2014" periodUnit="MNS" periodLength="3" /><Interim type="Q" periodNum="2" endMonth="6" endCalYear="2014" periodUnit="MNS" periodLength="3" /><Interim type="Q" periodNum="3" endMonth="9" endCalYear="2014" periodUnit="MNS" periodLength="3" /><Interim type="Q" periodNum="4" endMonth="12" endCalYear="2014" periodUnit="MNS" periodLength="3" /></Annual><Annual fyNum="-1" fYear="2015" endMonth="12" periodUnit="MNS" periodLength="12"><Interim type="Q" periodNum="1" endMonth="3" endCalYear="2015" periodUnit="MNS" periodLength="3" /><Interim type="Q" periodNum="2" endMonth="6" endCalYear="2015" periodUnit="MNS" periodLength="3" /><Interim type="Q" periodNum="3" endMonth="9" endCalYear="2015" periodUnit="MNS" periodLength="3" /><Interim type="Q" periodNum="4" endMonth="12" endCalYear="2015" periodUnit="MNS" periodLength="3" /></Annual><Annual fyNum="0" fYear="2016" endMonth="12" periodUnit="MNS" periodLength="12"><Interim type="Q" periodNum="1" endMonth="3" endCalYear="2016" periodUnit="MNS" periodLength="3" /><Interim type="Q" periodNum="2" endMonth="6" endCalYear="2016" periodUnit="MNS" periodLength="3" /><Interim type="Q" periodNum="3" endMonth="9" endCalYear="2016" periodUnit="MNS" periodLength="3" /><Interim type="Q" periodNum="4" endMonth="12" endCalYear="2016" periodUnit="MNS" periodLength="3" /></Annual><Annual fyNum="1" fYear="2017" endMonth="12" periodUnit="MNS" periodLength="12"><Interim type="Q" periodNum="1" endMonth="3" endCalYear="2017" periodUnit="MNS" periodLength="3" /><Interim type="Q" periodNum="2" endMonth="6" endCalYear="2017" periodUnit="MNS" periodLength="3" /><Interim type="Q" periodNum="3" endMonth="9" endCalYear="2017" periodUnit="MNS" periodLength="3" /><Interim type="Q" periodNum="4" endMonth="12" endCalYear="2017" periodUnit="MNS" periodLength="3" /></Annual><Annual fyNum="2" fYear="2018" endMonth="12" periodUnit="MNS" periodLength="12"><Interim type="Q" periodNum="1" endMonth="3" endCalYear="2018" periodUnit="MNS" periodLength="3" /><Interim type="Q" periodNum="2" endMonth="6" endCalYear="2018" periodUnit="MNS" periodLength="3" /><Interim type="Q" periodNum="3" endMonth="9" endCalYear="2018" periodUnit="MNS" periodLength="3" /><Interim type="Q" periodNum="4" endMonth="12" endCalYear="2018" periodUnit="MNS" periodLength="3" /></Annual><Annual fyNum="3" fYear="2019" endMonth="12" periodUnit="MNS" periodLength="12"><Interim type="Q" periodNum="1" endMonth="3" endCalYear="2019" periodUnit="MNS" periodLength="3" /><Interim type="Q" periodNum="2" endMonth="6" endCalYear="2019" periodUnit="MNS" periodLength="3" /><Interim type="Q" periodNum="3" endMonth="9" endCalYear="2019" periodUnit="MNS" periodLength="3" /><Interim type="Q" periodNum="4" endMonth="12" endCalYear="2019" periodUnit="MNS" periodLength="3" /></Annual><Annual fyNum="4" fYear="2020" endMonth="12" periodUnit="MNS" periodLength="12"><Interim type="Q" periodNum="1" endMonth="3" endCalYear="2020" periodUnit="MNS" periodLength="3" /><Interim type="Q" periodNum="2" endMonth="6" endCalYear="2020" periodUnit="MNS" periodLength="3" /><Interim type="Q" periodNum="3" endMonth="9" endCalYear="2020" periodUnit="MNS" periodLength="3" /><Interim type="Q" periodNum="4" endMonth="12" endCalYear="2020" periodUnit="MNS" periodLength="3" /></Annual><Annual fyNum="5" fYear="2021" endMonth="12" periodUnit="MNS" periodLength="12"><Interim type="Q" periodNum="1" endMonth="3" endCalYear="2021" periodUnit="MNS" periodLength="3" /><Interim type="Q" periodNum="2" endMonth="6" endCalYear="2021" periodUnit="MNS" periodLength="3" /><Interim type="Q" periodNum="3" endMonth="9" endCalYear="2021" periodUnit="MNS" periodLength="3" /><Interim type="Q" periodNum="4" endMonth="12" endCalYear="2021" periodUnit="MNS" periodLength="3" /></Annual></CompanyPeriods></CompanyInfo></Company><Actuals><FYActuals><FYActual type="CAPEX as of Aug31 2019" unit="M"><FYPeriod endCalYear="2016" endMonth="12" fYear="2016" periodType="A"><ActValue updated="2017-04-25T08:59:24" announceDate="2017-03-28T08:00:00">10.8445</ActValue></FYPeriod><FYPeriod endCalYear="2015" endMonth="12" fYear="2015" periodType="A"><ActValue updated="2016-05-20T00:16:50" announceDate="2016-03-23T07:47:00">18.6015</ActValue></FYPeriod></FYActual><FYActual type="NPROFIT as of Aug31 2019" unit="M"><FYPeriod endCalYear="2016" endMonth="12" fYear="2016" periodType="A"><ActValue updated="2017-03-30T08:38:53" announceDate="2017-03-28T08:00:00">7.1197</ActValue></FYPeriod><FYPeriod endCalYear="2015" endMonth="12" fYear="2015" periodType="A"><ActValue updated="2016-03-30T08:11:15" announceDate="2016-03-23T07:47:00">96.2671</ActValue></FYPeriod></FYActual><FYActual type="ROA as of Aug31 2019" unit="P"><FYPeriod endCalYear="2016" endMonth="12" fYear="2016" periodType="A"><ActValue updated="2017-04-25T08:59:23" announceDate="2017-03-28T08:00:00">0.6960</ActValue></FYPeriod><FYPeriod endCalYear="2015" endMonth="12" fYear="2015" periodType="A"><ActValue updated="2016-07-07T14:26:21" announceDate="2016-03-23T07:47:00">32.6280</ActValue></FYPeriod></FYActual><FYActual type="CPS as of Aug31 2019" unit="U"><FYPeriod endCalYear="2016" endMonth="12" fYear="2016" periodType="A"><ActValue updated="2017-04-25T08:59:26" announceDate="2017-03-28T08:00:00">0.1028</ActValue></FYPeriod><FYPeriod endCalYear="2015" endMonth="12" fYear="2015" periodType="A"><ActValue updated="2016-03-30T08:11:15" announceDate="2016-03-23T07:47:00">-0.0024</ActValue></FYPeriod></FYActual><FYActual type="EPS as of Aug31 2019" unit="U"><FYPeriod endCalYear="2016" endMonth="12" fYear="2016" periodType="A"><ActValue updated="2017-03-30T08:38:51" announceDate="2017-03-28T08:00:00">0.0113</ActValue></FYPeriod><FYPeriod endCalYear="2015" endMonth="12" fYear="2015" periodType="A"><ActValue updated="2016-03-30T08:11:11" announceDate="2016-03-23T07:47:00">0.1669</ActValue></FYPeriod></FYActual><FYActual type="REVENUE as of Aug31 2019" unit="M"><FYPeriod endCalYear="2016" endMonth="12" fYear="2016" periodType="A"><ActValue updated="2017-03-28T18:27:30" announceDate="2017-03-28T08:00:00">718.2207</ActValue></FYPeriod><FYPeriod endCalYear="2015" endMonth="12" fYear="2015" periodType="A"><ActValue updated="2016-03-30T12:13:52" announceDate="2016-03-23T07:47:00">500.9299</ActValue></FYPeriod></FYActual><FYActual type="EBIT as of Aug31 2019" unit="M"><FYPeriod endCalYear="2016" endMonth="12" fYear="2016" periodType="A"><ActValue updated="2017-03-30T08:38:53" announceDate="2017-03-28T08:00:00">31.1861</ActValue></FYPeriod><FYPeriod endCalYear="2015" endMonth="12" fYear="2015" periodType="A"><ActValue updated="2016-03-30T08:11:14" announceDate="2016-03-23T07:47:00">124.6688</ActValue></FYPeriod></FYActual><FYActual type="BVPS as of Aug31 2019" unit="U"><FYPeriod endCalYear="2016" endMonth="12" fYear="2016" periodType="A"><ActValue updated="2017-03-29T03:06:50" announceDate="2017-03-28T08:00:00">0.5484</ActValue></FYPeriod><FYPeriod endCalYear="2015" endMonth="12" fYear="2015" periodType="A"><ActValue updated="2016-03-30T12:13:48" announceDate="2016-03-23T07:47:00">0.7474</ActValue></FYPeriod></FYActual><FYActual type="NPROFITREP as of Aug31 2019" unit="M"><FYPeriod endCalYear="2015" endMonth="12" fYear="2015" periodType="A"><ActValue updated="2016-03-30T08:11:15" announceDate="2016-03-23T07:47:00">13.0086</ActValue></FYPeriod></FYActual><FYActual type="PPROFIT as of Aug31 2019" unit="M"><FYPeriod endCalYear="2016" endMonth="12" fYear="2016" periodType="A"><ActValue updated="2017-03-30T08:38:53" announceDate="2017-03-28T08:00:00">41.7234</ActValue></FYPeriod><FYPeriod endCalYear="2015" endMonth="12" fYear="2015" periodType="A"><ActValue updated="2016-03-30T08:11:14" announceDate="2016-03-23T07:47:00">125.7788</ActValue></FYPeriod></FYActual><FYActual type="EPSREP as of Aug31 2019" unit="U"><FYPeriod endCalYear="2015" endMonth="12" fYear="2015" periodType="A"><ActValue updated="2016-03-30T08:11:14" announceDate="2016-03-23T07:47:00">0.0227</ActValue></FYPeriod></FYActual><FYActual type="PPROFITREP as of Aug31 2019" unit="M"><FYPeriod endCalYear="2015" endMonth="12" fYear="2015" periodType="A"><ActValue updated="2016-03-30T08:11:15" announceDate="2016-03-23T07:47:00">42.1651</ActValue></FYPeriod></FYActual><FYActual type="EBITDA as of Aug31 2019" unit="M"><FYPeriod endCalYear="2016" endMonth="12" fYear="2016" periodType="A"><ActValue updated="2017-03-30T08:38:52" announceDate="2017-03-28T08:00:00">42.5287</ActValue></FYPeriod><FYPeriod endCalYear="2015" endMonth="12" fYear="2015" periodType="A"><ActValue updated="2016-03-30T08:11:14" announceDate="2016-03-23T07:47:00">130.8745</ActValue></FYPeriod></FYActual><FYActual type="NDEBT as of Aug31 2019" unit="M"><FYPeriod endCalYear="2016" endMonth="12" fYear="2016" periodType="A"><ActValue updated="2017-03-28T18:27:29" announceDate="2017-03-28T08:00:00">-354.5329</ActValue></FYPeriod><FYPeriod endCalYear="2015" endMonth="12" fYear="2015" periodType="A"><ActValue updated="2016-03-30T12:13:51" announceDate="2016-03-23T07:47:00">-500.1097</ActValue></FYPeriod></FYActual><FYActual type="ROE as of Aug31 2019" unit="P"><FYPeriod endCalYear="2016" endMonth="12" fYear="2016" periodType="A"><ActValue updated="2017-04-25T08:59:24" announceDate="2017-03-28T08:00:00">1.4210</ActValue></FYPeriod><FYPeriod endCalYear="2015" endMonth="12" fYear="2015" periodType="A"><ActValue updated="2016-07-07T14:26:22" announceDate="2016-03-23T07:47:00">16.1010</ActValue></FYPeriod></FYActual><FYActual type="DPS as of Aug31 2019" unit="U"><FYPeriod endCalYear="2016" endMonth="12" fYear="2016" periodType="A"><ActValue updated="2017-03-30T08:38:54" announceDate="2017-03-28T08:00:00">0.0000</ActValue></FYPeriod><FYPeriod endCalYear="2015" endMonth="12" fYear="2015" periodType="A"><ActValue updated="2016-03-30T08:14:52" announceDate="2016-03-23T07:47:00">0.0250</ActValue></FYPeriod></FYActual></FYActuals></Actuals><ConsEstimates><FYEstimates><FYEstimate type="BVPS as of Aug31 2019" unit="U"><FYPeriod endCalYear="2015" endMonth="12" fYear="2015" periodType="A"><ConsEstimate type="High"><ConsValue dateType="CURR">0.8308</ConsValue></ConsEstimate><ConsEstimate type="Low"><ConsValue dateType="CURR">0.7164</ConsValue></ConsEstimate><ConsEstimate type="Mean"><ConsValue dateType="CURR">0.7736</ConsValue></ConsEstimate><ConsEstimate type="Median"><ConsValue dateType="CURR">0.7736</ConsValue></ConsEstimate><ConsEstimate type="StdDev"><ConsValue dateType="CURR">0.0572</ConsValue></ConsEstimate><ConsEstimate type="NumOfEst"><ConsValue dateType="CURR">2</ConsValue></ConsEstimate></FYPeriod><FYPeriod endCalYear="2016" endMonth="12" fYear="2016" periodType="A"><ConsEstimate type="High"><ConsValue dateType="CURR">0.6914</ConsValue></ConsEstimate><ConsEstimate type="Low"><ConsValue dateType="CURR">0.6775</ConsValue></ConsEstimate><ConsEstimate type="Mean"><ConsValue dateType="CURR">0.6844</ConsValue></ConsEstimate><ConsEstimate type="Median"><ConsValue dateType="CURR">0.6844</ConsValue></ConsEstimate><ConsEstimate type="StdDev"><ConsValue dateType="CURR">0.0069</ConsValue></ConsEstimate><ConsEstimate type="NumOfEst"><ConsValue dateType="CURR">2</ConsValue></ConsEstimate></FYPeriod></FYEstimate><FYEstimate type="CAPEX as of Aug31 2019" unit="M"><FYPeriod endCalYear="2015" endMonth="12" fYear="2015" periodType="A"><ConsEstimate type="High"><ConsValue dateType="CURR">67.7346</ConsValue></ConsEstimate><ConsEstimate type="Low"><ConsValue dateType="CURR">67.7346</ConsValue></ConsEstimate><ConsEstimate type="Mean"><ConsValue dateType="CURR">67.7346</ConsValue></ConsEstimate><ConsEstimate type="Median"><ConsValue dateType="CURR">67.7346</ConsValue></ConsEstimate><ConsEstimate type="StdDev"><ConsValue dateType="CURR">0.0000</ConsValue></ConsEstimate><ConsEstimate type="NumOfEst"><ConsValue dateType="CURR">1</ConsValue></ConsEstimate></FYPeriod><FYPeriod endCalYear="2016" endMonth="12" fYear="2016" periodType="A"><ConsEstimate type="High"><ConsValue dateType="CURR">93.8170</ConsValue></ConsEstimate><ConsEstimate type="Low"><ConsValue dateType="CURR">93.8170</ConsValue></ConsEstimate><ConsEstimate type="Mean"><ConsValue dateType="CURR">93.8170</ConsValue></ConsEstimate><ConsEstimate type="Median"><ConsValue dateType="CURR">93.8170</ConsValue></ConsEstimate><ConsEstimate type="StdDev"><ConsValue dateType="CURR">0.0000</ConsValue></ConsEstimate><ConsEstimate type="NumOfEst"><ConsValue dateType="CURR">1</ConsValue></ConsEstimate></FYPeriod></FYEstimate><FYEstimate type="CPS as of Aug31 2019" unit="U"><FYPeriod endCalYear="2015" endMonth="12" fYear="2015" periodType="A"><ConsEstimate type="High"><ConsValue dateType="CURR">0.1141</ConsValue></ConsEstimate><ConsEstimate type="Low"><ConsValue dateType="CURR">0.1141</ConsValue></ConsEstimate><ConsEstimate type="Mean"><ConsValue dateType="CURR">0.1141</ConsValue></ConsEstimate><ConsEstimate type="Median"><ConsValue dateType="CURR">0.1141</ConsValue></ConsEstimate><ConsEstimate type="StdDev"><ConsValue dateType="CURR">0.0000</ConsValue></ConsEstimate><ConsEstimate type="NumOfEst"><ConsValue dateType="CURR">1</ConsValue></ConsEstimate></FYPeriod><FYPeriod endCalYear="2016" endMonth="12" fYear="2016" periodType="A"><ConsEstimate type="High"><ConsValue dateType="CURR">0.1235</ConsValue></ConsEstimate><ConsEstimate type="Low"><ConsValue dateType="CURR">0.1235</ConsValue></ConsEstimate><ConsEstimate type="Mean"><ConsValue dateType="CURR">0.1235</ConsValue></ConsEstimate><ConsEstimate type="Median"><ConsValue dateType="CURR">0.1235</ConsValue></ConsEstimate><ConsEstimate type="StdDev"><ConsValue dateType="CURR">0.0000</ConsValue></ConsEstimate><ConsEstimate type="NumOfEst"><ConsValue dateType="CURR">1</ConsValue></ConsEstimate></FYPeriod></FYEstimate><FYEstimate type="DPS as of Aug31 2019" unit="U"><FYPeriod endCalYear="2015" endMonth="12" fYear="2015" periodType="A"><ConsEstimate type="High"><ConsValue dateType="CURR">0.0118</ConsValue></ConsEstimate><ConsEstimate type="Low"><ConsValue dateType="CURR">0.0000</ConsValue></ConsEstimate><ConsEstimate type="Mean"><ConsValue dateType="CURR">0.0059</ConsValue></ConsEstimate><ConsEstimate type="Median"><ConsValue dateType="CURR">0.0059</ConsValue></ConsEstimate><ConsEstimate type="StdDev"><ConsValue dateType="CURR">0.0059</ConsValue></ConsEstimate><ConsEstimate type="NumOfEst"><ConsValue dateType="CURR">2</ConsValue></ConsEstimate></FYPeriod><FYPeriod endCalYear="2016" endMonth="12" fYear="2016" periodType="A"><ConsEstimate type="High"><ConsValue dateType="CURR">0.0245</ConsValue></ConsEstimate><ConsEstimate type="Low"><ConsValue dateType="CURR">0.0245</ConsValue></ConsEstimate><ConsEstimate type="Mean"><ConsValue dateType="CURR">0.0245</ConsValue></ConsEstimate><ConsEstimate type="Median"><ConsValue dateType="CURR">0.0245</ConsValue></ConsEstimate><ConsEstimate type="StdDev"><ConsValue dateType="CURR">0.0000</ConsValue></ConsEstimate><ConsEstimate type="NumOfEst"><ConsValue dateType="CURR">1</ConsValue></ConsEstimate></FYPeriod></FYEstimate><FYEstimate type="EBIT as of Aug31 2019" unit="M"><FYPeriod endCalYear="2015" endMonth="12" fYear="2015" periodType="A"><ConsEstimate type="High"><ConsValue dateType="CURR">184.5817</ConsValue></ConsEstimate><ConsEstimate type="Low"><ConsValue dateType="CURR">70.4581</ConsValue></ConsEstimate><ConsEstimate type="Mean"><ConsValue dateType="CURR">127.5199</ConsValue></ConsEstimate><ConsEstimate type="Median"><ConsValue dateType="CURR">127.5199</ConsValue></ConsEstimate><ConsEstimate type="StdDev"><ConsValue dateType="CURR">57.0618</ConsValue></ConsEstimate><ConsEstimate type="NumOfEst"><ConsValue dateType="CURR">2</ConsValue></ConsEstimate></FYPeriod><FYPeriod endCalYear="2016" endMonth="12" fYear="2016" periodType="A"><ConsEstimate type="High"><ConsValue dateType="CURR">148.8426</ConsValue></ConsEstimate><ConsEstimate type="Low"><ConsValue dateType="CURR">35.3920</ConsValue></ConsEstimate><ConsEstimate type="Mean"><ConsValue dateType="CURR">92.1173</ConsValue></ConsEstimate><ConsEstimate type="Median"><ConsValue dateType="CURR">92.1173</ConsValue></ConsEstimate><ConsEstimate type="StdDev"><ConsValue dateType="CURR">56.7253</ConsValue></ConsEstimate><ConsEstimate type="NumOfEst"><ConsValue dateType="CURR">2</ConsValue></ConsEstimate></FYPeriod></FYEstimate><FYEstimate type="EBITDA as of Aug31 2019" unit="M"><FYPeriod endCalYear="2015" endMonth="12" fYear="2015" periodType="A"><ConsEstimate type="High"><ConsValue dateType="CURR">184.5817</ConsValue></ConsEstimate><ConsEstimate type="Low"><ConsValue dateType="CURR">184.5817</ConsValue></ConsEstimate><ConsEstimate type="Mean"><ConsValue dateType="CURR">184.5817</ConsValue></ConsEstimate><ConsEstimate type="Median"><ConsValue dateType="CURR">184.5817</ConsValue></ConsEstimate><ConsEstimate type="StdDev"><ConsValue dateType="CURR">0.0000</ConsValue></ConsEstimate><ConsEstimate type="NumOfEst"><ConsValue dateType="CURR">1</ConsValue></ConsEstimate></FYPeriod><FYPeriod endCalYear="2016" endMonth="12" fYear="2016" periodType="A"><ConsEstimate type="High"><ConsValue dateType="CURR">148.8426</ConsValue></ConsEstimate><ConsEstimate type="Low"><ConsValue dateType="CURR">148.8426</ConsValue></ConsEstimate><ConsEstimate type="Mean"><ConsValue dateType="CURR">148.8426</ConsValue></ConsEstimate><ConsEstimate type="Median"><ConsValue dateType="CURR">148.8426</ConsValue></ConsEstimate><ConsEstimate type="StdDev"><ConsValue dateType="CURR">0.0000</ConsValue></ConsEstimate><ConsEstimate type="NumOfEst"><ConsValue dateType="CURR">1</ConsValue></ConsEstimate></FYPeriod></FYEstimate><FYEstimate type="EPS as of Aug31 2019" unit="U"><FYPeriod endCalYear="2015" endMonth="12" fYear="2015" periodType="A"><ConsEstimate type="High"><ConsValue dateType="CURR">0.0639</ConsValue></ConsEstimate><ConsEstimate type="Low"><ConsValue dateType="CURR">0.0404</ConsValue></ConsEstimate><ConsEstimate type="Mean"><ConsValue dateType="CURR">0.0522</ConsValue></ConsEstimate><ConsEstimate type="Median"><ConsValue dateType="CURR">0.0522</ConsValue></ConsEstimate><ConsEstimate type="StdDev"><ConsValue dateType="CURR">0.0118</ConsValue></ConsEstimate><ConsEstimate type="NumOfEst"><ConsValue dateType="CURR">2</ConsValue></ConsEstimate></FYPeriod><FYPeriod endCalYear="2016" endMonth="12" fYear="2016" periodType="A"><ConsEstimate type="High"><ConsValue dateType="CURR">0.0186</ConsValue></ConsEstimate><ConsEstimate type="Low"><ConsValue dateType="CURR">0.0045</ConsValue></ConsEstimate><ConsEstimate type="Mean"><ConsValue dateType="CURR">0.0116</ConsValue></ConsEstimate><ConsEstimate type="Median"><ConsValue dateType="CURR">0.0116</ConsValue></ConsEstimate><ConsEstimate type="StdDev"><ConsValue dateType="CURR">0.0071</ConsValue></ConsEstimate><ConsEstimate type="NumOfEst"><ConsValue dateType="CURR">2</ConsValue></ConsEstimate></FYPeriod></FYEstimate><FYEstimate type="NDEBT as of Aug31 2019" unit="M"><FYPeriod endCalYear="2015" endMonth="12" fYear="2015" periodType="A"><ConsEstimate type="High"><ConsValue dateType="CURR">-701.0886</ConsValue></ConsEstimate><ConsEstimate type="Low"><ConsValue dateType="CURR">-701.0886</ConsValue></ConsEstimate><ConsEstimate type="Mean"><ConsValue dateType="CURR">-701.0886</ConsValue></ConsEstimate><ConsEstimate type="Median"><ConsValue dateType="CURR">-701.0886</ConsValue></ConsEstimate><ConsEstimate type="StdDev"><ConsValue dateType="CURR">0.0000</ConsValue></ConsEstimate><ConsEstimate type="NumOfEst"><ConsValue dateType="CURR">1</ConsValue></ConsEstimate></FYPeriod><FYPeriod endCalYear="2016" endMonth="12" fYear="2016" periodType="A"><ConsEstimate type="High"><ConsValue dateType="CURR">-256.3857</ConsValue></ConsEstimate><ConsEstimate type="Low"><ConsValue dateType="CURR">-256.3857</ConsValue></ConsEstimate><ConsEstimate type="Mean"><ConsValue dateType="CURR">-256.3857</ConsValue></ConsEstimate><ConsEstimate type="Median"><ConsValue dateType="CURR">-256.3857</ConsValue></ConsEstimate><ConsEstimate type="StdDev"><ConsValue dateType="CURR">0.0000</ConsValue></ConsEstimate><ConsEstimate type="NumOfEst"><ConsValue dateType="CURR">1</ConsValue></ConsEstimate></FYPeriod></FYEstimate><FYEstimate type="NPROFIT as of Aug31 2019" unit="M"><FYPeriod endCalYear="2015" endMonth="12" fYear="2015" periodType="A"><ConsEstimate type="High"><ConsValue dateType="CURR">92.6021</ConsValue></ConsEstimate><ConsEstimate type="Low"><ConsValue dateType="CURR">91.2616</ConsValue></ConsEstimate><ConsEstimate type="Mean"><ConsValue dateType="CURR">91.9319</ConsValue></ConsEstimate><ConsEstimate type="Median"><ConsValue dateType="CURR">91.9319</ConsValue></ConsEstimate><ConsEstimate type="StdDev"><ConsValue dateType="CURR">0.6703</ConsValue></ConsEstimate><ConsEstimate type="NumOfEst"><ConsValue dateType="CURR">2</ConsValue></ConsEstimate></FYPeriod><FYPeriod endCalYear="2016" endMonth="12" fYear="2016" periodType="A"><ConsEstimate type="High"><ConsValue dateType="CURR">95.6717</ConsValue></ConsEstimate><ConsEstimate type="Low"><ConsValue dateType="CURR">33.7067</ConsValue></ConsEstimate><ConsEstimate type="Mean"><ConsValue dateType="CURR">64.6892</ConsValue></ConsEstimate><ConsEstimate type="Median"><ConsValue dateType="CURR">64.6892</ConsValue></ConsEstimate><ConsEstimate type="StdDev"><ConsValue dateType="CURR">30.9825</ConsValue></ConsEstimate><ConsEstimate type="NumOfEst"><ConsValue dateType="CURR">2</ConsValue></ConsEstimate></FYPeriod></FYEstimate><FYEstimate type="NPROFITREP as of Aug31 2019" unit="M"><FYPeriod endCalYear="2015" endMonth="12" fYear="2015" periodType="A"><ConsEstimate type="High"><ConsValue dateType="CURR">37.8935</ConsValue></ConsEstimate><ConsEstimate type="Low"><ConsValue dateType="CURR">37.8935</ConsValue></ConsEstimate><ConsEstimate type="Mean"><ConsValue dateType="CURR">37.8935</ConsValue></ConsEstimate><ConsEstimate type="Median"><ConsValue dateType="CURR">37.8935</ConsValue></ConsEstimate><ConsEstimate type="StdDev"><ConsValue dateType="CURR">0.0000</ConsValue></ConsEstimate><ConsEstimate type="NumOfEst"><ConsValue dateType="CURR">1</ConsValue></ConsEstimate></FYPeriod></FYEstimate><FYEstimate type="PPROFIT as of Aug31 2019" unit="M"><FYPeriod endCalYear="2015" endMonth="12" fYear="2015" periodType="A"><ConsEstimate type="High"><ConsValue dateType="CURR">67.2229</ConsValue></ConsEstimate><ConsEstimate type="Low"><ConsValue dateType="CURR">60.9848</ConsValue></ConsEstimate><ConsEstimate type="Mean"><ConsValue dateType="CURR">64.1039</ConsValue></ConsEstimate><ConsEstimate type="Median"><ConsValue dateType="CURR">64.1039</ConsValue></ConsEstimate><ConsEstimate type="StdDev"><ConsValue dateType="CURR">3.1191</ConsValue></ConsEstimate><ConsEstimate type="NumOfEst"><ConsValue dateType="CURR">2</ConsValue></ConsEstimate></FYPeriod><FYPeriod endCalYear="2016" endMonth="12" fYear="2016" periodType="A"><ConsEstimate type="High"><ConsValue dateType="CURR">63.0101</ConsValue></ConsEstimate><ConsEstimate type="Low"><ConsValue dateType="CURR">34.7179</ConsValue></ConsEstimate><ConsEstimate type="Mean"><ConsValue dateType="CURR">48.8640</ConsValue></ConsEstimate><ConsEstimate type="Median"><ConsValue dateType="CURR">48.8640</ConsValue></ConsEstimate><ConsEstimate type="StdDev"><ConsValue dateType="CURR">14.1461</ConsValue></ConsEstimate><ConsEstimate type="NumOfEst"><ConsValue dateType="CURR">2</ConsValue></ConsEstimate></FYPeriod></FYEstimate><FYEstimate type="PPROFITREP as of Aug31 2019" unit="M"><FYPeriod endCalYear="2015" endMonth="12" fYear="2015" periodType="A"><ConsEstimate type="High"><ConsValue dateType="CURR">60.9848</ConsValue></ConsEstimate><ConsEstimate type="Low"><ConsValue dateType="CURR">60.9848</ConsValue></ConsEstimate><ConsEstimate type="Mean"><ConsValue dateType="CURR">60.9848</ConsValue></ConsEstimate><ConsEstimate type="Median"><ConsValue dateType="CURR">60.9848</ConsValue></ConsEstimate><ConsEstimate type="StdDev"><ConsValue dateType="CURR">0.0000</ConsValue></ConsEstimate><ConsEstimate type="NumOfEst"><ConsValue dateType="CURR">1</ConsValue></ConsEstimate></FYPeriod></FYEstimate><FYEstimate type="REVENUE as of Aug31 2019" unit="M"><FYPeriod endCalYear="2015" endMonth="12" fYear="2015" periodType="A"><ConsEstimate type="High"><ConsValue dateType="CURR">509.1323</ConsValue></ConsEstimate><ConsEstimate type="Low"><ConsValue dateType="CURR">504.6935</ConsValue></ConsEstimate><ConsEstimate type="Mean"><ConsValue dateType="CURR">506.9129</ConsValue></ConsEstimate><ConsEstimate type="Median"><ConsValue dateType="CURR">506.9129</ConsValue></ConsEstimate><ConsEstimate type="StdDev"><ConsValue dateType="CURR">2.2194</ConsValue></ConsEstimate><ConsEstimate type="NumOfEst"><ConsValue dateType="CURR">2</ConsValue></ConsEstimate></FYPeriod><FYPeriod endCalYear="2016" endMonth="12" fYear="2016" periodType="A"><ConsEstimate type="High"><ConsValue dateType="CURR">697.2465</ConsValue></ConsEstimate><ConsEstimate type="Low"><ConsValue dateType="CURR">665.5952</ConsValue></ConsEstimate><ConsEstimate type="Mean"><ConsValue dateType="CURR">681.4208</ConsValue></ConsEstimate><ConsEstimate type="Median"><ConsValue dateType="CURR">681.4208</ConsValue></ConsEstimate><ConsEstimate type="StdDev"><ConsValue dateType="CURR">15.8256</ConsValue></ConsEstimate><ConsEstimate type="NumOfEst"><ConsValue dateType="CURR">2</ConsValue></ConsEstimate></FYPeriod></FYEstimate><FYEstimate type="ROA as of Aug31 2019" unit="P"><FYPeriod endCalYear="2015" endMonth="12" fYear="2015" periodType="A"><ConsEstimate type="High"><ConsValue dateType="CURR">47.0000</ConsValue></ConsEstimate><ConsEstimate type="Low"><ConsValue dateType="CURR">30.0780</ConsValue></ConsEstimate><ConsEstimate type="Mean"><ConsValue dateType="CURR">38.5390</ConsValue></ConsEstimate><ConsEstimate type="Median"><ConsValue dateType="CURR">38.5390</ConsValue></ConsEstimate><ConsEstimate type="StdDev"><ConsValue dateType="CURR">8.4610</ConsValue></ConsEstimate><ConsEstimate type="NumOfEst"><ConsValue dateType="CURR">2</ConsValue></ConsEstimate></FYPeriod><FYPeriod endCalYear="2016" endMonth="12" fYear="2016" periodType="A"><ConsEstimate type="High"><ConsValue dateType="CURR">16.4920</ConsValue></ConsEstimate><ConsEstimate type="Low"><ConsValue dateType="CURR">3.0000</ConsValue></ConsEstimate><ConsEstimate type="Mean"><ConsValue dateType="CURR">9.7460</ConsValue></ConsEstimate><ConsEstimate type="Median"><ConsValue dateType="CURR">9.7460</ConsValue></ConsEstimate><ConsEstimate type="StdDev"><ConsValue dateType="CURR">6.7460</ConsValue></ConsEstimate><ConsEstimate type="NumOfEst"><ConsValue dateType="CURR">2</ConsValue></ConsEstimate></FYPeriod></FYEstimate><FYEstimate type="ROE as of Aug31 2019" unit="P"><FYPeriod endCalYear="2015" endMonth="12" fYear="2015" periodType="A"><ConsEstimate type="High"><ConsValue dateType="CURR">23.4680</ConsValue></ConsEstimate><ConsEstimate type="Low"><ConsValue dateType="CURR">6.6000</ConsValue></ConsEstimate><ConsEstimate type="Mean"><ConsValue dateType="CURR">15.0340</ConsValue></ConsEstimate><ConsEstimate type="Median"><ConsValue dateType="CURR">15.0340</ConsValue></ConsEstimate><ConsEstimate type="StdDev"><ConsValue dateType="CURR">8.4340</ConsValue></ConsEstimate><ConsEstimate type="NumOfEst"><ConsValue dateType="CURR">2</ConsValue></ConsEstimate></FYPeriod><FYPeriod endCalYear="2016" endMonth="12" fYear="2016" periodType="A"><ConsEstimate type="High"><ConsValue dateType="CURR">17.0340</ConsValue></ConsEstimate><ConsEstimate type="Low"><ConsValue dateType="CURR">6.0000</ConsValue></ConsEstimate><ConsEstimate type="Mean"><ConsValue dateType="CURR">11.5170</ConsValue></ConsEstimate><ConsEstimate type="Median"><ConsValue dateType="CURR">11.5170</ConsValue></ConsEstimate><ConsEstimate type="StdDev"><ConsValue dateType="CURR">5.5170</ConsValue></ConsEstimate><ConsEstimate type="NumOfEst"><ConsValue dateType="CURR">2</ConsValue></ConsEstimate></FYPeriod></FYEstimate></FYEstimates><NPEstimates /><Recommendations><STOpinion /></Recommendations></ConsEstimates></REarnEstCons>