<?xml version="1.0" encoding="utf-8"?><REarnEstCons><Company><CoName><Name type="Long">China Glass Holdings Limited</Name></CoName><CoIds><CoId type="CoId">GL_37955</CoId><CoId type="RepNo">AAB19</CoId><CoId type="IssueId">1</CoId><CoId type="IssuerID">56103</CoId><CoId type="RedIssueID">39097</CoId><CoId type="IsPrimaryIssue">1</CoId></CoIds><SecurityInfo><Security code="1"><Exchange code="HKG">Hong Kong Stock Exchange</Exchange><Country set="MX" code="HKG">Hong Kong</Country><SecIds><SecId set="LOCAL" type="RIC">3300.HK</SecId><SecId set="LOCAL" type="Display RIC">3300.HK</SecId><SecId set="LOCAL" type="TICKER">3300</SecId><SecId set="LOCAL" type="ISIN">BMG2111H1236</SecId><SecId set="LOCAL" type="SEDOL">B0BHF82</SecId><SecId set="LOCAL" type="CUSIP">G2111H123</SecId></SecIds><MarketData><MarketDataItem type="CLPRICE" currCode="CNY" unit="U" updated="2017-12-11T00:00:00">0.576750</MarketDataItem><MarketDataItem type="SHARESOUT" currCode="CNY" unit="U">1810147058</MarketDataItem><MarketDataItem type="MARKETCAP" currCode="CNY" unit="M">1044.0019</MarketDataItem><MarketDataItem type="52WKHIGH" currCode="CNY" unit="U" updated="2017-02-23T00:00:00">0.8312</MarketDataItem><MarketDataItem type="52WKLOW" currCode="CNY" unit="U" updated="2017-08-18T00:00:00">0.5513</MarketDataItem></MarketData><LastSplit splitDate="2011-04-18T00:00:00">2.0000</LastSplit></Security></SecurityInfo><CompanyInfo><Sector set="RBSS2004" code="52">Industrials</Sector><Sector set="RBSS2004" code="522">Industrial Services</Sector><Sector set="RBSS2004" code="5221">Construction, Engineering &amp; Materials</Sector><Sector set="MX" code="CAPGDS">Capital Goods</Sector><Industry set="RBSS2004" code="52211">Construction - Supplies &amp; Fixtures</Industry><Industry set="MX" code="BLDFIX">Constr. - Supplies &amp; Fixtures</Industry><Primary type="Earnings">PRX</Primary><Primary type="Consensus">Mean</Primary><Primary type="Estimate">EPS</Primary><Primary type="Periodicity">S</Primary><Currency set="ISO" type="CONSENSUS" code="CNY">Renminbi</Currency><CurFiscalPeriod fYear="2017" fyem="12" periodType="S" periodNum="1" /><CompanyPeriods><Annual fyNum="-5" fYear="2011" endMonth="12" periodUnit="MNS" periodLength="12" /><Annual fyNum="-4" fYear="2012" endMonth="12" periodUnit="MNS" periodLength="12"><Interim type="S" periodNum="1" endMonth="6" endCalYear="2012" periodUnit="MNS" periodLength="6" /><Interim type="S" periodNum="2" endMonth="12" endCalYear="2012" periodUnit="MNS" periodLength="6" /></Annual><Annual fyNum="-3" fYear="2013" endMonth="12" periodUnit="MNS" periodLength="12"><Interim type="S" periodNum="1" endMonth="6" endCalYear="2013" periodUnit="MNS" periodLength="6" /><Interim type="S" periodNum="2" endMonth="12" endCalYear="2013" periodUnit="MNS" periodLength="6" /></Annual><Annual fyNum="-2" fYear="2014" endMonth="12" periodUnit="MNS" periodLength="12"><Interim type="S" periodNum="1" endMonth="6" endCalYear="2014" periodUnit="MNS" periodLength="6" /><Interim type="S" periodNum="2" endMonth="12" endCalYear="2014" periodUnit="MNS" periodLength="6" /></Annual><Annual fyNum="-1" fYear="2015" endMonth="12" periodUnit="MNS" periodLength="12"><Interim type="S" periodNum="1" endMonth="6" endCalYear="2015" periodUnit="MNS" periodLength="6" /><Interim type="S" periodNum="2" endMonth="12" endCalYear="2015" periodUnit="MNS" periodLength="6" /></Annual><Annual fyNum="0" fYear="2016" endMonth="12" periodUnit="MNS" periodLength="12"><Interim type="S" periodNum="1" endMonth="6" endCalYear="2016" periodUnit="MNS" periodLength="6" /><Interim type="S" periodNum="2" endMonth="12" endCalYear="2016" periodUnit="MNS" periodLength="6" /></Annual><Annual fyNum="1" fYear="2017" endMonth="12" periodUnit="MNS" periodLength="12"><Interim type="S" periodNum="1" endMonth="6" endCalYear="2017" periodUnit="MNS" periodLength="6" /><Interim type="S" periodNum="2" endMonth="12" endCalYear="2017" periodUnit="MNS" periodLength="6" /></Annual><Annual fyNum="2" fYear="2018" endMonth="12" periodUnit="MNS" periodLength="12"><Interim type="S" periodNum="1" endMonth="6" endCalYear="2018" periodUnit="MNS" periodLength="6" /><Interim type="S" periodNum="2" endMonth="12" endCalYear="2018" periodUnit="MNS" periodLength="6" /></Annual><Annual fyNum="3" fYear="2019" endMonth="12" periodUnit="MNS" periodLength="12"><Interim type="S" periodNum="1" endMonth="6" endCalYear="2019" periodUnit="MNS" periodLength="6" /><Interim type="S" periodNum="2" endMonth="12" endCalYear="2019" periodUnit="MNS" periodLength="6" /></Annual><Annual fyNum="4" fYear="2020" endMonth="12" periodUnit="MNS" periodLength="12"><Interim type="S" periodNum="1" endMonth="6" endCalYear="2020" periodUnit="MNS" periodLength="6" /><Interim type="S" periodNum="2" endMonth="12" endCalYear="2020" periodUnit="MNS" periodLength="6" /></Annual><Annual fyNum="5" fYear="2021" endMonth="12" periodUnit="MNS" periodLength="12"><Interim type="S" periodNum="1" endMonth="6" endCalYear="2021" periodUnit="MNS" periodLength="6" /><Interim type="S" periodNum="2" endMonth="12" endCalYear="2021" periodUnit="MNS" periodLength="6" /></Annual></CompanyPeriods></CompanyInfo></Company><Actuals><FYActuals><FYActual type="CAPEX as of Aug31 2019" unit="M"><FYPeriod endCalYear="2012" endMonth="12" fYear="2012" periodType="A"><ActValue updated="2013-04-12T08:00:49" announceDate="2013-03-26T23:21:00">492.1010</ActValue></FYPeriod></FYActual><FYActual type="NPROFIT as of Aug31 2019" unit="M"><FYPeriod endCalYear="2012" endMonth="12" fYear="2012" periodType="A"><ActValue updated="2013-03-29T13:59:41" announceDate="2013-03-26T23:21:00">-173.5870</ActValue></FYPeriod><FYPeriod endCalYear="2011" endMonth="12" fYear="2011" periodType="A"><ActValue updated="2012-03-28T00:58:26" announceDate="2012-03-27T23:13:00">181.6020</ActValue></FYPeriod></FYActual><FYActual type="ROA as of Aug31 2019" unit="P"><FYPeriod endCalYear="2012" endMonth="12" fYear="2012" periodType="A"><ActValue updated="2013-04-02T02:35:29" announceDate="2013-03-26T23:21:00">-2.9660</ActValue></FYPeriod><FYPeriod endCalYear="2011" endMonth="12" fYear="2011" periodType="A"><ActValue updated="2012-04-09T10:15:00" announceDate="2012-03-27T23:13:00">3.3110</ActValue></FYPeriod></FYActual><FYActual type="EPS as of Aug31 2019" unit="U"><FYPeriod endCalYear="2012" endMonth="12" fYear="2012" periodType="A"><ActValue updated="2013-03-29T13:59:43" announceDate="2013-03-26T23:21:00">-0.1130</ActValue></FYPeriod><FYPeriod endCalYear="2011" endMonth="12" fYear="2011" periodType="A"><ActValue updated="2012-03-28T00:58:28" announceDate="2012-03-27T23:13:00">0.1220</ActValue></FYPeriod></FYActual><FYActual type="REVENUE as of Aug31 2019" unit="M"><FYPeriod endCalYear="2012" endMonth="12" fYear="2012" periodType="A"><ActValue updated="2013-03-29T13:59:37" announceDate="2013-03-26T23:21:00">2550.1750</ActValue></FYPeriod><FYPeriod endCalYear="2011" endMonth="12" fYear="2011" periodType="A"><ActValue updated="2012-03-28T00:58:25" announceDate="2012-03-27T23:13:00">2946.0480</ActValue></FYPeriod></FYActual><FYActual type="EBIT as of Aug31 2019" unit="M"><FYPeriod endCalYear="2012" endMonth="12" fYear="2012" periodType="A"><ActValue updated="2013-03-29T13:59:38" announceDate="2013-03-26T23:21:00">-82.2480</ActValue></FYPeriod><FYPeriod endCalYear="2011" endMonth="12" fYear="2011" periodType="A"><ActValue updated="2012-04-09T10:14:52" announceDate="2012-03-27T23:13:00">341.6640</ActValue></FYPeriod></FYActual><FYActual type="BVPS as of Aug31 2019" unit="U"><FYPeriod endCalYear="2012" endMonth="12" fYear="2012" periodType="A"><ActValue updated="2013-04-12T08:00:48" announceDate="2013-03-26T23:21:00">1.3400</ActValue></FYPeriod><FYPeriod endCalYear="2011" endMonth="12" fYear="2011" periodType="A"><ActValue updated="2012-04-09T10:14:56" announceDate="2012-03-27T23:13:00">1.4490</ActValue></FYPeriod></FYActual><FYActual type="NPROFITREP as of Aug31 2019" unit="M"><FYPeriod endCalYear="2012" endMonth="12" fYear="2012" periodType="A"><ActValue updated="2013-03-29T13:59:42" announceDate="2013-03-26T23:21:00">-173.5870</ActValue></FYPeriod></FYActual><FYActual type="PPROFIT as of Aug31 2019" unit="M"><FYPeriod endCalYear="2012" endMonth="12" fYear="2012" periodType="A"><ActValue updated="2013-03-29T13:59:39" announceDate="2013-03-26T23:21:00">-188.9710</ActValue></FYPeriod><FYPeriod endCalYear="2011" endMonth="12" fYear="2011" periodType="A"><ActValue updated="2012-03-28T00:58:27" announceDate="2012-03-27T23:13:00">281.4980</ActValue></FYPeriod></FYActual><FYActual type="EPSREP as of Aug31 2019" unit="U"><FYPeriod endCalYear="2012" endMonth="12" fYear="2012" periodType="A"><ActValue updated="2013-03-29T13:59:44" announceDate="2013-03-26T23:21:00">-0.1130</ActValue></FYPeriod></FYActual><FYActual type="PPROFITREP as of Aug31 2019" unit="M"><FYPeriod endCalYear="2012" endMonth="12" fYear="2012" periodType="A"><ActValue updated="2013-03-29T13:59:40" announceDate="2013-03-26T23:21:00">-188.9710</ActValue></FYPeriod></FYActual><FYActual type="EBITDA as of Aug31 2019" unit="M"><FYPeriod endCalYear="2012" endMonth="12" fYear="2012" periodType="A"><ActValue updated="2013-04-02T02:35:25" announceDate="2013-03-26T23:21:00">165.9050</ActValue></FYPeriod><FYPeriod endCalYear="2011" endMonth="12" fYear="2011" periodType="A"><ActValue updated="2012-04-09T10:14:51" announceDate="2012-03-27T23:13:00">587.4470</ActValue></FYPeriod></FYActual><FYActual type="NDEBT as of Aug31 2019" unit="M"><FYPeriod endCalYear="2012" endMonth="12" fYear="2012" periodType="A"><ActValue updated="2013-04-02T02:35:27" announceDate="2013-03-26T23:21:00">1300.0570</ActValue></FYPeriod><FYPeriod endCalYear="2011" endMonth="12" fYear="2011" periodType="A"><ActValue updated="2012-04-09T10:14:58" announceDate="2012-03-27T23:13:00">1047.7760</ActValue></FYPeriod></FYActual><FYActual type="ROE as of Aug31 2019" unit="P"><FYPeriod endCalYear="2012" endMonth="12" fYear="2012" periodType="A"><ActValue updated="2013-04-02T02:35:28" announceDate="2013-03-26T23:21:00">-8.0330</ActValue></FYPeriod><FYPeriod endCalYear="2011" endMonth="12" fYear="2011" periodType="A"><ActValue updated="2012-04-09T10:14:59" announceDate="2012-03-27T23:13:00">9.8200</ActValue></FYPeriod></FYActual><FYActual type="DPS as of Aug31 2019" unit="U"><FYPeriod endCalYear="2012" endMonth="12" fYear="2012" periodType="A"><ActValue updated="2013-04-02T02:35:26" announceDate="2013-03-26T23:21:00">0.0000</ActValue></FYPeriod><FYPeriod endCalYear="2011" endMonth="12" fYear="2011" periodType="A"><ActValue updated="2012-04-09T10:14:53" announceDate="2012-03-27T23:13:00">0.0080</ActValue></FYPeriod></FYActual></FYActuals></Actuals><ConsEstimates><FYEstimates><FYEstimate type="BVPS as of Aug31 2019" unit="U"><FYPeriod endCalYear="2011" endMonth="12" fYear="2011" periodType="A"><ConsEstimate type="High"><ConsValue dateType="CURR">1.4730</ConsValue></ConsEstimate><ConsEstimate type="Low"><ConsValue dateType="CURR">1.4730</ConsValue></ConsEstimate><ConsEstimate type="Mean"><ConsValue dateType="CURR">1.4730</ConsValue></ConsEstimate><ConsEstimate type="Median"><ConsValue dateType="CURR">1.4730</ConsValue></ConsEstimate><ConsEstimate type="StdDev"><ConsValue dateType="CURR">0.0000</ConsValue></ConsEstimate><ConsEstimate type="NumOfEst"><ConsValue dateType="CURR">1</ConsValue></ConsEstimate></FYPeriod><FYPeriod endCalYear="2012" endMonth="12" fYear="2012" periodType="A"><ConsEstimate type="High"><ConsValue dateType="CURR">1.4480</ConsValue></ConsEstimate><ConsEstimate type="Low"><ConsValue dateType="CURR">1.3640</ConsValue></ConsEstimate><ConsEstimate type="Mean"><ConsValue dateType="CURR">1.4060</ConsValue></ConsEstimate><ConsEstimate type="Median"><ConsValue dateType="CURR">1.4060</ConsValue></ConsEstimate><ConsEstimate type="StdDev"><ConsValue dateType="CURR">0.0420</ConsValue></ConsEstimate><ConsEstimate type="NumOfEst"><ConsValue dateType="CURR">2</ConsValue></ConsEstimate></FYPeriod></FYEstimate><FYEstimate type="CAPEX as of Aug31 2019" unit="M"><FYPeriod endCalYear="2012" endMonth="12" fYear="2012" periodType="A"><ConsEstimate type="High"><ConsValue dateType="CURR">800.0000</ConsValue></ConsEstimate><ConsEstimate type="Low"><ConsValue dateType="CURR">800.0000</ConsValue></ConsEstimate><ConsEstimate type="Mean"><ConsValue dateType="CURR">800.0000</ConsValue></ConsEstimate><ConsEstimate type="Median"><ConsValue dateType="CURR">800.0000</ConsValue></ConsEstimate><ConsEstimate type="StdDev"><ConsValue dateType="CURR">0.0000</ConsValue></ConsEstimate><ConsEstimate type="NumOfEst"><ConsValue dateType="CURR">1</ConsValue></ConsEstimate></FYPeriod></FYEstimate><FYEstimate type="DPS as of Aug31 2019" unit="U"><FYPeriod endCalYear="2011" endMonth="12" fYear="2011" periodType="A"><ConsEstimate type="High"><ConsValue dateType="CURR">0.0190</ConsValue></ConsEstimate><ConsEstimate type="Low"><ConsValue dateType="CURR">0.0190</ConsValue></ConsEstimate><ConsEstimate type="Mean"><ConsValue dateType="CURR">0.0190</ConsValue></ConsEstimate><ConsEstimate type="Median"><ConsValue dateType="CURR">0.0190</ConsValue></ConsEstimate><ConsEstimate type="StdDev"><ConsValue dateType="CURR">0.0000</ConsValue></ConsEstimate><ConsEstimate type="NumOfEst"><ConsValue dateType="CURR">1</ConsValue></ConsEstimate></FYPeriod><FYPeriod endCalYear="2012" endMonth="12" fYear="2012" periodType="A"><ConsEstimate type="High"><ConsValue dateType="CURR">0.0000</ConsValue></ConsEstimate><ConsEstimate type="Low"><ConsValue dateType="CURR">0.0000</ConsValue></ConsEstimate><ConsEstimate type="Mean"><ConsValue dateType="CURR">0.0000</ConsValue></ConsEstimate><ConsEstimate type="Median"><ConsValue dateType="CURR">0.0000</ConsValue></ConsEstimate><ConsEstimate type="StdDev"><ConsValue dateType="CURR">0.0000</ConsValue></ConsEstimate><ConsEstimate type="NumOfEst"><ConsValue dateType="CURR">1</ConsValue></ConsEstimate></FYPeriod></FYEstimate><FYEstimate type="EBIT as of Aug31 2019" unit="M"><FYPeriod endCalYear="2011" endMonth="12" fYear="2011" periodType="A"><ConsEstimate type="High"><ConsValue dateType="CURR">300.9430</ConsValue></ConsEstimate><ConsEstimate type="Low"><ConsValue dateType="CURR">300.9430</ConsValue></ConsEstimate><ConsEstimate type="Mean"><ConsValue dateType="CURR">300.9430</ConsValue></ConsEstimate><ConsEstimate type="Median"><ConsValue dateType="CURR">300.9430</ConsValue></ConsEstimate><ConsEstimate type="StdDev"><ConsValue dateType="CURR">0.0000</ConsValue></ConsEstimate><ConsEstimate type="NumOfEst"><ConsValue dateType="CURR">1</ConsValue></ConsEstimate></FYPeriod><FYPeriod endCalYear="2012" endMonth="12" fYear="2012" periodType="A"><ConsEstimate type="High"><ConsValue dateType="CURR">-30.1000</ConsValue></ConsEstimate><ConsEstimate type="Low"><ConsValue dateType="CURR">-121.2030</ConsValue></ConsEstimate><ConsEstimate type="Mean"><ConsValue dateType="CURR">-75.6515</ConsValue></ConsEstimate><ConsEstimate type="Median"><ConsValue dateType="CURR">-75.6515</ConsValue></ConsEstimate><ConsEstimate type="StdDev"><ConsValue dateType="CURR">45.5515</ConsValue></ConsEstimate><ConsEstimate type="NumOfEst"><ConsValue dateType="CURR">2</ConsValue></ConsEstimate></FYPeriod></FYEstimate><FYEstimate type="EBITDA as of Aug31 2019" unit="M"><FYPeriod endCalYear="2011" endMonth="12" fYear="2011" periodType="A"><ConsEstimate type="High"><ConsValue dateType="CURR">588.0500</ConsValue></ConsEstimate><ConsEstimate type="Low"><ConsValue dateType="CURR">588.0500</ConsValue></ConsEstimate><ConsEstimate type="Mean"><ConsValue dateType="CURR">588.0500</ConsValue></ConsEstimate><ConsEstimate type="Median"><ConsValue dateType="CURR">588.0500</ConsValue></ConsEstimate><ConsEstimate type="StdDev"><ConsValue dateType="CURR">0.0000</ConsValue></ConsEstimate><ConsEstimate type="NumOfEst"><ConsValue dateType="CURR">1</ConsValue></ConsEstimate></FYPeriod><FYPeriod endCalYear="2012" endMonth="12" fYear="2012" periodType="A"><ConsEstimate type="High"><ConsValue dateType="CURR">568.9000</ConsValue></ConsEstimate><ConsEstimate type="Low"><ConsValue dateType="CURR">170.6310</ConsValue></ConsEstimate><ConsEstimate type="Mean"><ConsValue dateType="CURR">369.7655</ConsValue></ConsEstimate><ConsEstimate type="Median"><ConsValue dateType="CURR">369.7655</ConsValue></ConsEstimate><ConsEstimate type="StdDev"><ConsValue dateType="CURR">199.1345</ConsValue></ConsEstimate><ConsEstimate type="NumOfEst"><ConsValue dateType="CURR">2</ConsValue></ConsEstimate></FYPeriod></FYEstimate><FYEstimate type="EPS as of Aug31 2019" unit="U"><FYPeriod endCalYear="2011" endMonth="12" fYear="2011" periodType="A"><ConsEstimate type="High"><ConsValue dateType="CURR">0.1380</ConsValue></ConsEstimate><ConsEstimate type="Low"><ConsValue dateType="CURR">0.1380</ConsValue></ConsEstimate><ConsEstimate type="Mean"><ConsValue dateType="CURR">0.1380</ConsValue></ConsEstimate><ConsEstimate type="Median"><ConsValue dateType="CURR">0.1380</ConsValue></ConsEstimate><ConsEstimate type="StdDev"><ConsValue dateType="CURR">0.0000</ConsValue></ConsEstimate><ConsEstimate type="NumOfEst"><ConsValue dateType="CURR">1</ConsValue></ConsEstimate></FYPeriod><FYPeriod endCalYear="2012" endMonth="12" fYear="2012" periodType="A"><ConsEstimate type="High"><ConsValue dateType="CURR">-0.0800</ConsValue></ConsEstimate><ConsEstimate type="Low"><ConsValue dateType="CURR">-0.0980</ConsValue></ConsEstimate><ConsEstimate type="Mean"><ConsValue dateType="CURR">-0.0890</ConsValue></ConsEstimate><ConsEstimate type="Median"><ConsValue dateType="CURR">-0.0890</ConsValue></ConsEstimate><ConsEstimate type="StdDev"><ConsValue dateType="CURR">0.0090</ConsValue></ConsEstimate><ConsEstimate type="NumOfEst"><ConsValue dateType="CURR">2</ConsValue></ConsEstimate></FYPeriod></FYEstimate><FYEstimate type="EPSREP as of Aug31 2019" unit="U"><FYPeriod endCalYear="2012" endMonth="12" fYear="2012" periodType="A"><ConsEstimate type="High"><ConsValue dateType="CURR">-0.0800</ConsValue></ConsEstimate><ConsEstimate type="Low"><ConsValue dateType="CURR">-0.0800</ConsValue></ConsEstimate><ConsEstimate type="Mean"><ConsValue dateType="CURR">-0.0800</ConsValue></ConsEstimate><ConsEstimate type="Median"><ConsValue dateType="CURR">-0.0800</ConsValue></ConsEstimate><ConsEstimate type="StdDev"><ConsValue dateType="CURR">0.0000</ConsValue></ConsEstimate><ConsEstimate type="NumOfEst"><ConsValue dateType="CURR">1</ConsValue></ConsEstimate></FYPeriod></FYEstimate><FYEstimate type="NDEBT as of Aug31 2019" unit="M"><FYPeriod endCalYear="2011" endMonth="12" fYear="2011" periodType="A"><ConsEstimate type="High"><ConsValue dateType="CURR">910.7460</ConsValue></ConsEstimate><ConsEstimate type="Low"><ConsValue dateType="CURR">910.7460</ConsValue></ConsEstimate><ConsEstimate type="Mean"><ConsValue dateType="CURR">910.7460</ConsValue></ConsEstimate><ConsEstimate type="Median"><ConsValue dateType="CURR">910.7460</ConsValue></ConsEstimate><ConsEstimate type="StdDev"><ConsValue dateType="CURR">0.0000</ConsValue></ConsEstimate><ConsEstimate type="NumOfEst"><ConsValue dateType="CURR">1</ConsValue></ConsEstimate></FYPeriod><FYPeriod endCalYear="2012" endMonth="12" fYear="2012" periodType="A"><ConsEstimate type="High"><ConsValue dateType="CURR">1644.2950</ConsValue></ConsEstimate><ConsEstimate type="Low"><ConsValue dateType="CURR">1644.2950</ConsValue></ConsEstimate><ConsEstimate type="Mean"><ConsValue dateType="CURR">1644.2950</ConsValue></ConsEstimate><ConsEstimate type="Median"><ConsValue dateType="CURR">1644.2950</ConsValue></ConsEstimate><ConsEstimate type="StdDev"><ConsValue dateType="CURR">0.0000</ConsValue></ConsEstimate><ConsEstimate type="NumOfEst"><ConsValue dateType="CURR">1</ConsValue></ConsEstimate></FYPeriod></FYEstimate><FYEstimate type="NPROFIT as of Aug31 2019" unit="M"><FYPeriod endCalYear="2011" endMonth="12" fYear="2011" periodType="A"><ConsEstimate type="High"><ConsValue dateType="CURR">203.2480</ConsValue></ConsEstimate><ConsEstimate type="Low"><ConsValue dateType="CURR">203.2480</ConsValue></ConsEstimate><ConsEstimate type="Mean"><ConsValue dateType="CURR">203.2480</ConsValue></ConsEstimate><ConsEstimate type="Median"><ConsValue dateType="CURR">203.2480</ConsValue></ConsEstimate><ConsEstimate type="StdDev"><ConsValue dateType="CURR">0.0000</ConsValue></ConsEstimate><ConsEstimate type="NumOfEst"><ConsValue dateType="CURR">1</ConsValue></ConsEstimate></FYPeriod><FYPeriod endCalYear="2012" endMonth="12" fYear="2012" periodType="A"><ConsEstimate type="High"><ConsValue dateType="CURR">-118.0000</ConsValue></ConsEstimate><ConsEstimate type="Low"><ConsValue dateType="CURR">-157.4720</ConsValue></ConsEstimate><ConsEstimate type="Mean"><ConsValue dateType="CURR">-137.7360</ConsValue></ConsEstimate><ConsEstimate type="Median"><ConsValue dateType="CURR">-137.7360</ConsValue></ConsEstimate><ConsEstimate type="StdDev"><ConsValue dateType="CURR">19.7360</ConsValue></ConsEstimate><ConsEstimate type="NumOfEst"><ConsValue dateType="CURR">2</ConsValue></ConsEstimate></FYPeriod></FYEstimate><FYEstimate type="NPROFITREP as of Aug31 2019" unit="M"><FYPeriod endCalYear="2012" endMonth="12" fYear="2012" periodType="A"><ConsEstimate type="High"><ConsValue dateType="CURR">-118.0000</ConsValue></ConsEstimate><ConsEstimate type="Low"><ConsValue dateType="CURR">-118.0000</ConsValue></ConsEstimate><ConsEstimate type="Mean"><ConsValue dateType="CURR">-118.0000</ConsValue></ConsEstimate><ConsEstimate type="Median"><ConsValue dateType="CURR">-118.0000</ConsValue></ConsEstimate><ConsEstimate type="StdDev"><ConsValue dateType="CURR">0.0000</ConsValue></ConsEstimate><ConsEstimate type="NumOfEst"><ConsValue dateType="CURR">1</ConsValue></ConsEstimate></FYPeriod></FYEstimate><FYEstimate type="PPROFIT as of Aug31 2019" unit="M"><FYPeriod endCalYear="2011" endMonth="12" fYear="2011" periodType="A"><ConsEstimate type="High"><ConsValue dateType="CURR">299.5100</ConsValue></ConsEstimate><ConsEstimate type="Low"><ConsValue dateType="CURR">299.5100</ConsValue></ConsEstimate><ConsEstimate type="Mean"><ConsValue dateType="CURR">299.5100</ConsValue></ConsEstimate><ConsEstimate type="Median"><ConsValue dateType="CURR">299.5100</ConsValue></ConsEstimate><ConsEstimate type="StdDev"><ConsValue dateType="CURR">0.0000</ConsValue></ConsEstimate><ConsEstimate type="NumOfEst"><ConsValue dateType="CURR">1</ConsValue></ConsEstimate></FYPeriod><FYPeriod endCalYear="2012" endMonth="12" fYear="2012" periodType="A"><ConsEstimate type="High"><ConsValue dateType="CURR">-176.2000</ConsValue></ConsEstimate><ConsEstimate type="Low"><ConsValue dateType="CURR">-218.7110</ConsValue></ConsEstimate><ConsEstimate type="Mean"><ConsValue dateType="CURR">-197.4555</ConsValue></ConsEstimate><ConsEstimate type="Median"><ConsValue dateType="CURR">-197.4555</ConsValue></ConsEstimate><ConsEstimate type="StdDev"><ConsValue dateType="CURR">21.2555</ConsValue></ConsEstimate><ConsEstimate type="NumOfEst"><ConsValue dateType="CURR">2</ConsValue></ConsEstimate></FYPeriod></FYEstimate><FYEstimate type="PPROFITREP as of Aug31 2019" unit="M"><FYPeriod endCalYear="2012" endMonth="12" fYear="2012" periodType="A"><ConsEstimate type="High"><ConsValue dateType="CURR">-176.2000</ConsValue></ConsEstimate><ConsEstimate type="Low"><ConsValue dateType="CURR">-176.2000</ConsValue></ConsEstimate><ConsEstimate type="Mean"><ConsValue dateType="CURR">-176.2000</ConsValue></ConsEstimate><ConsEstimate type="Median"><ConsValue dateType="CURR">-176.2000</ConsValue></ConsEstimate><ConsEstimate type="StdDev"><ConsValue dateType="CURR">0.0000</ConsValue></ConsEstimate><ConsEstimate type="NumOfEst"><ConsValue dateType="CURR">1</ConsValue></ConsEstimate></FYPeriod></FYEstimate><FYEstimate type="REVENUE as of Aug31 2019" unit="M"><FYPeriod endCalYear="2011" endMonth="12" fYear="2011" periodType="A"><ConsEstimate type="High"><ConsValue dateType="CURR">3354.0600</ConsValue></ConsEstimate><ConsEstimate type="Low"><ConsValue dateType="CURR">3354.0600</ConsValue></ConsEstimate><ConsEstimate type="Mean"><ConsValue dateType="CURR">3354.0600</ConsValue></ConsEstimate><ConsEstimate type="Median"><ConsValue dateType="CURR">3354.0600</ConsValue></ConsEstimate><ConsEstimate type="StdDev"><ConsValue dateType="CURR">0.0000</ConsValue></ConsEstimate><ConsEstimate type="NumOfEst"><ConsValue dateType="CURR">1</ConsValue></ConsEstimate></FYPeriod><FYPeriod endCalYear="2012" endMonth="12" fYear="2012" periodType="A"><ConsEstimate type="High"><ConsValue dateType="CURR">2444.4510</ConsValue></ConsEstimate><ConsEstimate type="Low"><ConsValue dateType="CURR">2420.0000</ConsValue></ConsEstimate><ConsEstimate type="Mean"><ConsValue dateType="CURR">2432.2255</ConsValue></ConsEstimate><ConsEstimate type="Median"><ConsValue dateType="CURR">2432.2255</ConsValue></ConsEstimate><ConsEstimate type="StdDev"><ConsValue dateType="CURR">12.2255</ConsValue></ConsEstimate><ConsEstimate type="NumOfEst"><ConsValue dateType="CURR">2</ConsValue></ConsEstimate></FYPeriod></FYEstimate><FYEstimate type="ROA as of Aug31 2019" unit="P"><FYPeriod endCalYear="2011" endMonth="12" fYear="2011" periodType="A"><ConsEstimate type="High"><ConsValue dateType="CURR">3.9810</ConsValue></ConsEstimate><ConsEstimate type="Low"><ConsValue dateType="CURR">3.9810</ConsValue></ConsEstimate><ConsEstimate type="Mean"><ConsValue dateType="CURR">3.9810</ConsValue></ConsEstimate><ConsEstimate type="Median"><ConsValue dateType="CURR">3.9810</ConsValue></ConsEstimate><ConsEstimate type="StdDev"><ConsValue dateType="CURR">0.0000</ConsValue></ConsEstimate><ConsEstimate type="NumOfEst"><ConsValue dateType="CURR">1</ConsValue></ConsEstimate></FYPeriod><FYPeriod endCalYear="2012" endMonth="12" fYear="2012" periodType="A"><ConsEstimate type="High"><ConsValue dateType="CURR">-2.0000</ConsValue></ConsEstimate><ConsEstimate type="Low"><ConsValue dateType="CURR">-2.6580</ConsValue></ConsEstimate><ConsEstimate type="Mean"><ConsValue dateType="CURR">-2.3290</ConsValue></ConsEstimate><ConsEstimate type="Median"><ConsValue dateType="CURR">-2.3290</ConsValue></ConsEstimate><ConsEstimate type="StdDev"><ConsValue dateType="CURR">0.3290</ConsValue></ConsEstimate><ConsEstimate type="NumOfEst"><ConsValue dateType="CURR">2</ConsValue></ConsEstimate></FYPeriod></FYEstimate><FYEstimate type="ROE as of Aug31 2019" unit="P"><FYPeriod endCalYear="2011" endMonth="12" fYear="2011" periodType="A"><ConsEstimate type="High"><ConsValue dateType="CURR">9.2280</ConsValue></ConsEstimate><ConsEstimate type="Low"><ConsValue dateType="CURR">9.2280</ConsValue></ConsEstimate><ConsEstimate type="Mean"><ConsValue dateType="CURR">9.2280</ConsValue></ConsEstimate><ConsEstimate type="Median"><ConsValue dateType="CURR">9.2280</ConsValue></ConsEstimate><ConsEstimate type="StdDev"><ConsValue dateType="CURR">0.0000</ConsValue></ConsEstimate><ConsEstimate type="NumOfEst"><ConsValue dateType="CURR">1</ConsValue></ConsEstimate></FYPeriod><FYPeriod endCalYear="2012" endMonth="12" fYear="2012" periodType="A"><ConsEstimate type="High"><ConsValue dateType="CURR">-5.4000</ConsValue></ConsEstimate><ConsEstimate type="Low"><ConsValue dateType="CURR">-6.5070</ConsValue></ConsEstimate><ConsEstimate type="Mean"><ConsValue dateType="CURR">-5.9535</ConsValue></ConsEstimate><ConsEstimate type="Median"><ConsValue dateType="CURR">-5.9535</ConsValue></ConsEstimate><ConsEstimate type="StdDev"><ConsValue dateType="CURR">0.5535</ConsValue></ConsEstimate><ConsEstimate type="NumOfEst"><ConsValue dateType="CURR">2</ConsValue></ConsEstimate></FYPeriod></FYEstimate></FYEstimates><NPEstimates /><Recommendations><STOpinion /></Recommendations></ConsEstimates></REarnEstCons>